{
  "anim_reacttocliff_stop_02": [
    {
      "durationTime_ms": 99,
      "triggerTime_ms": 0,
      "Name": "LiftHeightKeyFrame",
      "heightVariability_mm": 0,
      "height_mm": 32
    },
    {
      "durationTime_ms": 66,
      "triggerTime_ms": 198,
      "Name": "LiftHeightKeyFrame",
      "heightVariability_mm": 0,
      "height_mm": 37
    },
    {
      "durationTime_ms": 66,
      "triggerTime_ms": 264,
      "Name": "LiftHeightKeyFrame",
      "heightVariability_mm": 0,
      "height_mm": 32
    },
    {
      "durationTime_ms": 66,
      "triggerTime_ms": 1155,
      "Name": "LiftHeightKeyFrame",
      "heightVariability_mm": 0,
      "height_mm": 37
    },
    {
      "durationTime_ms": 66,
      "triggerTime_ms": 1221,
      "Name": "LiftHeightKeyFrame",
      "heightVariability_mm": 0,
      "height_mm": 32
    },
    {
      "durationTime_ms": 66,
      "triggerTime_ms": 1287,
      "Name": "LiftHeightKeyFrame",
      "heightVariability_mm": 0,
      "height_mm": 36
    },
    {
      "durationTime_ms": 66,
      "triggerTime_ms": 1353,
      "Name": "LiftHeightKeyFrame",
      "heightVariability_mm": 0,
      "height_mm": 34
    },
    {
      "durationTime_ms": 66,
      "triggerTime_ms": 1419,
      "Name": "LiftHeightKeyFrame",
      "heightVariability_mm": 0,
      "height_mm": 37
    },
    {
      "durationTime_ms": 66,
      "triggerTime_ms": 1485,
      "Name": "LiftHeightKeyFrame",
      "heightVariability_mm": 0,
      "height_mm": 33
    },
    {
      "durationTime_ms": 66,
      "triggerTime_ms": 1551,
      "Name": "LiftHeightKeyFrame",
      "heightVariability_mm": 0,
      "height_mm": 37
    },
    {
      "durationTime_ms": 66,
      "triggerTime_ms": 1617,
      "Name": "LiftHeightKeyFrame",
      "heightVariability_mm": 0,
      "height_mm": 34
    },
    {
      "durationTime_ms": 66,
      "triggerTime_ms": 1683,
      "Name": "LiftHeightKeyFrame",
      "heightVariability_mm": 0,
      "height_mm": 32
    },
    {
      "durationTime_ms": 66,
      "triggerTime_ms": 3234,
      "Name": "LiftHeightKeyFrame",
      "heightVariability_mm": 0,
      "height_mm": 39
    },
    {
      "durationTime_ms": 99,
      "triggerTime_ms": 3300,
      "Name": "LiftHeightKeyFrame",
      "heightVariability_mm": 0,
      "height_mm": 32
    },
    {
      "angleVariability_deg": 0,
      "angle_deg": 0,
      "triggerTime_ms": 0,
      "Name": "HeadAngleKeyFrame",
      "durationTime_ms": 66
    },
    {
      "angleVariability_deg": 0,
      "angle_deg": 10,
      "triggerTime_ms": 66,
      "Name": "HeadAngleKeyFrame",
      "durationTime_ms": 66
    },
    {
      "angleVariability_deg": 0,
      "angle_deg": -22,
      "triggerTime_ms": 132,
      "Name": "HeadAngleKeyFrame",
      "durationTime_ms": 66
    },
    {
      "angleVariability_deg": 0,
      "angle_deg": 0,
      "triggerTime_ms": 198,
      "Name": "HeadAngleKeyFrame",
      "durationTime_ms": 132
    },
    {
      "angleVariability_deg": 0,
      "angle_deg": -13,
      "triggerTime_ms": 330,
      "Name": "HeadAngleKeyFrame",
      "durationTime_ms": 99
    },
    {
      "angleVariability_deg": 0,
      "angle_deg": -10,
      "triggerTime_ms": 858,
      "Name": "HeadAngleKeyFrame",
      "durationTime_ms": 66
    },
    {
      "angleVariability_deg": 0,
      "angle_deg": -19,
      "triggerTime_ms": 924,
      "Name": "HeadAngleKeyFrame",
      "durationTime_ms": 66
    },
    {
      "angleVariability_deg": 0,
      "angle_deg": -13,
      "triggerTime_ms": 990,
      "Name": "HeadAngleKeyFrame",
      "durationTime_ms": 66
    },
    {
      "angleVariability_deg": 0,
      "angle_deg": -17,
      "triggerTime_ms": 1155,
      "Name": "HeadAngleKeyFrame",
      "durationTime_ms": 66
    },
    {
      "angleVariability_deg": 0,
      "angle_deg": -8,
      "triggerTime_ms": 1221,
      "Name": "HeadAngleKeyFrame",
      "durationTime_ms": 66
    },
    {
      "angleVariability_deg": 0,
      "angle_deg": -15,
      "triggerTime_ms": 1287,
      "Name": "HeadAngleKeyFrame",
      "durationTime_ms": 66
    },
    {
      "angleVariability_deg": 0,
      "angle_deg": -10,
      "triggerTime_ms": 1353,
      "Name": "HeadAngleKeyFrame",
      "durationTime_ms": 66
    },
    {
      "angleVariability_deg": 0,
      "angle_deg": -16,
      "triggerTime_ms": 1419,
      "Name": "HeadAngleKeyFrame",
      "durationTime_ms": 66
    },
    {
      "angleVariability_deg": 0,
      "angle_deg": -9,
      "triggerTime_ms": 1485,
      "Name": "HeadAngleKeyFrame",
      "durationTime_ms": 66
    },
    {
      "angleVariability_deg": 0,
      "angle_deg": -16,
      "triggerTime_ms": 1551,
      "Name": "HeadAngleKeyFrame",
      "durationTime_ms": 66
    },
    {
      "angleVariability_deg": 0,
      "angle_deg": -3,
      "triggerTime_ms": 1617,
      "Name": "HeadAngleKeyFrame",
      "durationTime_ms": 66
    },
    {
      "angleVariability_deg": 0,
      "angle_deg": -14,
      "triggerTime_ms": 1683,
      "Name": "HeadAngleKeyFrame",
      "durationTime_ms": 99
    },
    {
      "angleVariability_deg": 0,
      "angle_deg": -6,
      "triggerTime_ms": 1782,
      "Name": "HeadAngleKeyFrame",
      "durationTime_ms": 99
    },
    {
      "angleVariability_deg": 0,
      "angle_deg": -8,
      "triggerTime_ms": 1881,
      "Name": "HeadAngleKeyFrame",
      "durationTime_ms": 66
    },
    {
      "angleVariability_deg": 0,
      "angle_deg": -15,
      "triggerTime_ms": 2310,
      "Name": "HeadAngleKeyFrame",
      "durationTime_ms": 66
    },
    {
      "angleVariability_deg": 0,
      "angle_deg": -10,
      "triggerTime_ms": 2607,
      "Name": "HeadAngleKeyFrame",
      "durationTime_ms": 66
    },
    {
      "angleVariability_deg": 0,
      "angle_deg": -4,
      "triggerTime_ms": 3201,
      "Name": "HeadAngleKeyFrame",
      "durationTime_ms": 66
    },
    {
      "angleVariability_deg": 0,
      "angle_deg": -22,
      "triggerTime_ms": 3267,
      "Name": "HeadAngleKeyFrame",
      "durationTime_ms": 132
    },
    {
      "angleVariability_deg": 0,
      "angle_deg": 5,
      "triggerTime_ms": 3399,
      "Name": "HeadAngleKeyFrame",
      "durationTime_ms": 99
    },
    {
      "angleVariability_deg": 0,
      "angle_deg": -2,
      "triggerTime_ms": 3498,
      "Name": "HeadAngleKeyFrame",
      "durationTime_ms": 66
    },
    {
      "angleVariability_deg": 0,
      "angle_deg": 0,
      "triggerTime_ms": 3564,
      "Name": "HeadAngleKeyFrame",
      "durationTime_ms": 99
    },
    {
      "Name": "ProceduralFaceKeyFrame",
      "faceScaleY": 1.0,
      "scanlineOpacity": 1.0,
      "faceScaleX": 1.0,
      "leftEye": [
        8.107326060759803,
        0.0,
        1.5174507300664741,
        1.1453089027930028,
        0.0,
        0.6,
        0.6,
        0.6,
        0.6,
        0.6,
        0.6,
        0.6,
        0.6,
        0.0,
        0.0,
        0.0,
        0.0,
        0.0,
        0.0,
        1,
        1.0,
        0.0,
        0.0,
        0.0,
        0
      ],
      "faceAngle": 0.0,
      "durationTime_ms": 0,
      "faceCenterY": 0.0,
      "faceCenterX": 0.0,
      "rightEye": [
        -7.315991464547729,
        0.0,
        1.5174507300664741,
        1.144941064931666,
        0.0,
        0.6,
        0.6,
        0.6,
        0.6,
        0.6,
        0.6,
        0.6,
        0.6,
        0.0,
        0.0,
        0.0,
        0.0,
        0.0,
        0.0,
        1,
        1.0,
        0.0,
        0.0,
        0.0,
        0
      ],
      "triggerTime_ms": 0
    },
    {
      "Name": "ProceduralFaceKeyFrame",
      "faceScaleY": 1.0,
      "scanlineOpacity": 1.0,
      "faceScaleX": 1.0,
      "leftEye": [
        8.107326060759803,
        0.0,
        1.5174507300664741,
        1.1453089027930028,
        0.0,
        0.6,
        0.6,
        0.6,
        0.6,
        0.6,
        0.6,
        0.6,
        0.6,
        0.0,
        0.0,
        0.0,
        0.0,
        0.0,
        0.0,
        1,
        1.0,
        0.0,
        0.0,
        0.0,
        0
      ],
      "faceAngle": 0.0,
      "durationTime_ms": 0,
      "faceCenterY": 0.0,
      "faceCenterX": 0.0,
      "rightEye": [
        -7.315991464547729,
        0.0,
        1.5174507300664741,
        1.144941064931666,
        0.0,
        0.6,
        0.6,
        0.6,
        0.6,
        0.6,
        0.6,
        0.6,
        0.6,
        0.0,
        0.0,
        0.0,
        0.0,
        0.0,
        0.0,
        1,
        1.0,
        0.0,
        0.0,
        0.0,
        0
      ],
      "triggerTime_ms": 33
    },
    {
      "Name": "ProceduralFaceKeyFrame",
      "faceScaleY": 0.9424459866997074,
      "scanlineOpacity": 1.0,
      "faceScaleX": 1.0069444447588074,
      "leftEye": [
        8.222399756370024,
        0.0,
        1.541160898802434,
        1.1453089027930028,
        0.0,
        0.6,
        0.6,
        0.6,
        0.6,
        0.6115157837962748,
        0.6115157837962748,
        0.6,
        0.6,
        0.0,
        0.0,
        0.0,
        0.0,
        0.0,
        0.0,
        1,
        1.0,
        0.0,
        0.0,
        0.00019422842433980403,
        0
      ],
      "faceAngle": 0.0,
      "durationTime_ms": 0,
      "faceCenterY": 0.551361486020923,
      "faceCenterX": 0.0,
      "rightEye": [
        -7.420330487081287,
        -0.033267514430988854,
        1.5467303053483714,
        1.1472326096958703,
        0.0,
        0.6,
        0.6,
        0.6,
        0.6,
        0.6115157837962748,
        0.6115157837962748,
        0.6,
        0.6,
        0.0,
        0.0,
        0.0,
        0.0,
        0.0,
        0.0,
        1,
        1.0,
        0.0,
        0.0,
        0.00018627303225293712,
        0
      ],
      "triggerTime_ms": 66
    },
    {
      "Name": "ProceduralFaceKeyFrame",
      "faceScaleY": 1.0701134269207602,
      "scanlineOpacity": 1.0,
      "faceScaleX": 1.0878904271294354,
      "leftEye": [
        10.56223156711112,
        0.0,
        1.5208365469252094,
        1.1453089027930028,
        0.0,
        0.6000010596366219,
        0.6000010596366219,
        0.6000009546929864,
        0.6000009546929864,
        0.8456700543205273,
        0.8456700543205273,
        0.6000010596366219,
        0.6000010596366219,
        0.0,
        0.0,
        0.0,
        0.0,
        0.0,
        0.0,
        1,
        1.0,
        -0.2910526037276788,
        0.0,
        0.00524416745718248,
        0
      ],
      "faceAngle": 0.0,
      "durationTime_ms": 0,
      "faceCenterY": -3.531003122224585,
      "faceCenterX": 0.0,
      "rightEye": [
        -9.541890611930484,
        -0.7097069745277906,
        1.589059684970839,
        1.190860770102206,
        0.0,
        0.6000010647157397,
        0.6000010647157397,
        0.6000009546944273,
        0.6000009546944273,
        0.8456700543205273,
        0.8456700543205273,
        0.6000010647157397,
        0.6000010647157397,
        0.0,
        0.0,
        0.0,
        0.0,
        0.0,
        0.0,
        1,
        1.0,
        -0.2910526037276788,
        0.0,
        0.005029371870837629,
        0
      ],
      "triggerTime_ms": 99
    },
    {
      "Name": "ProceduralFaceKeyFrame",
      "faceScaleY": 0.8475493879330886,
      "scanlineOpacity": 1.0,
      "faceScaleX": 1.075587449584672,
      "leftEye": [
        8.10732798324414,
        0.0,
        1.7513372014173543,
        1.1452821488839107,
        0.0,
        0.6000027100003369,
        0.6000027100003369,
        0.6000024416090023,
        0.6000024416090023,
        0.7192716767425551,
        0.7192716767425551,
        0.6000027100003369,
        0.6000027100003369,
        0.003166078218638013,
        0.0,
        0.0,
        0.0,
        0.0,
        0.0,
        1,
        1.0,
        -0.5,
        0.022799797802441686,
        0.00524416745718248,
        0
      ],
      "faceAngle": 0.0,
      "durationTime_ms": 0,
      "faceCenterY": 3.223786438026764,
      "faceCenterX": 0.0,
      "rightEye": [
        -7.315964048564055,
        0.3150672186280232,
        1.6907047493507688,
        1.1919181067117712,
        0.0,
        0.6000027229900835,
        0.6000027229900835,
        0.6000024416126871,
        0.6000024416126871,
        0.7192716767425551,
        0.7192716767425551,
        0.6000027229900835,
        0.6000027229900835,
        0.003013430026057917,
        0.0011604000701112213,
        0.0,
        0.0,
        0.0,
        0.0,
        1,
        1.0,
        -0.5,
        -0.02475633975432312,
        0.005029371870837629,
        0
      ],
      "triggerTime_ms": 132
    },
    {
      "Name": "ProceduralFaceKeyFrame",
      "faceScaleY": 0.10735038053467715,
      "scanlineOpacity": 1.0,
      "faceScaleX": 1.3133816418027617,
      "leftEye": [
        8.10732798324414,
        0.0,
        1.979227518930409,
        1.1452821488839107,
        0.0,
        0.08090406491636098,
        0.08090406491636098,
        0.08090403030084876,
        0.08090403030084876,
        0.08090361926352922,
        0.08090361926352922,
        0.08090406491636098,
        0.08090406491636098,
        0.0031655244432441387,
        0.0,
        0.0,
        0.0,
        0.0,
        0.0,
        1,
        1.0,
        -0.5,
        0.04516596182000436,
        0.00524416745718248,
        0
      ],
      "faceAngle": 0.0,
      "durationTime_ms": 0,
      "faceCenterY": 17.758559364788805,
      "faceCenterX": 0.0,
      "rightEye": [
        -7.315964048564055,
        0.3150672186280232,
        1.8202011314884645,
        1.1846579179998846,
        0.0,
        0.08090406659170098,
        0.08090406659170098,
        0.080904030301324,
        0.080904030301324,
        0.08090361926352922,
        0.08090361926352922,
        0.08090406659170098,
        0.08090406659170098,
        0.0030128762506640427,
        0.0011604000701112213,
        0.0,
        0.0,
        0.0,
        0.0,
        1,
        1.0,
        -0.5,
        -0.04904183387218797,
        0.005029371870837629,
        0
      ],
      "triggerTime_ms": 165
    },
    {
      "Name": "ProceduralFaceKeyFrame",
      "faceScaleY": 0.09949961159609819,
      "scanlineOpacity": 1.0,
      "faceScaleX": 1.8930226240222066,
      "leftEye": [
        8.107327909508683,
        0.0,
        1.979227518930409,
        1.1452821488839107,
        0.0,
        0.016838310592184432,
        0.016838310592184432,
        0.016838304828653502,
        0.016838304828653502,
        0.01683823639036811,
        0.01683823639036811,
        0.016838310592184432,
        0.016838310592184432,
        0.0031616480154865734,
        0.0,
        0.0,
        0.0,
        0.0,
        0.0,
        1,
        1.0,
        -0.5,
        0.07196430293150023,
        0.29424548642961734,
        0
      ],
      "faceAngle": 0.0,
      "durationTime_ms": 0,
      "faceCenterY": 19.655013362877646,
      "faceCenterX": 0.0,
      "rightEye": [
        -7.727116646721186,
        0.3150672186280232,
        1.6630716826652845,
        1.1449400548293385,
        0.0,
        0.016838310871130868,
        0.016838310871130868,
        0.01683830482873263,
        0.01683830482873263,
        0.01683823639036811,
        0.01683823639036811,
        0.016838310871130868,
        0.016838310871130868,
        0.0030089998229064774,
        0.0011604000701112213,
        0.0,
        0.0,
        0.0,
        0.0,
        1,
        1.0,
        -0.5,
        -0.0781398479491986,
        0.2957231808272449,
        0
      ],
      "triggerTime_ms": 198
    },
    {
      "Name": "ProceduralFaceKeyFrame",
      "faceScaleY": 0.6170110389807438,
      "scanlineOpacity": 1.0,
      "faceScaleX": 1.0807955456678475,
      "leftEye": [
        8.415150362901166,
        0.0,
        1.7580649391578083,
        1.1618849354576621,
        0.0,
        0.6135706818949752,
        0.6135838345699222,
        0.6016947878954625,
        0.6693059490870092,
        0.6797771832674256,
        0.7169176713053824,
        0.6433019411641996,
        0.6808500183190004,
        0.0031511262830019593,
        0.0,
        0.0,
        0.0,
        0.0,
        0.0,
        1,
        1.0,
        -0.24999999999999967,
        0.10207938655111101,
        0.32459512107918054,
        0
      ],
      "faceAngle": 0.0,
      "durationTime_ms": 0,
      "faceCenterY": 16.73303441610023,
      "faceCenterX": 0.0,
      "rightEye": [
        -8.241431666270508,
        0.3150672186280232,
        1.523923691978759,
        1.1498237963898936,
        0.0,
        0.6135706948847219,
        0.6135838475596688,
        0.6016947878991474,
        0.6693059490906942,
        0.6797771832674256,
        0.7169176713053824,
        0.6433019541539462,
        0.680850031308747,
        0.0029984780904219743,
        0.0011604000701112213,
        0.0,
        0.0,
        0.0,
        0.0,
        1,
        1.0,
        -0.24999999999999967,
        -0.11083922749093755,
        0.32669118998383484,
        0
      ],
      "triggerTime_ms": 231
    },
    {
      "Name": "ProceduralFaceKeyFrame",
      "faceScaleY": 0.9837675465205781,
      "scanlineOpacity": 1.0,
      "faceScaleX": 1.0267727547600505,
      "leftEye": [
        9.149188520990933,
        0.0,
        1.6393607979760152,
        1.1618849354576621,
        0.0,
        0.6135706818949752,
        0.6135838345699222,
        0.6016947878954625,
        0.6693059490870092,
        0.7149114834914213,
        0.7539830563801151,
        0.612511067154247,
        0.6383859014889122,
        0.0031306365934266056,
        0.0,
        0.0,
        0.0,
        0.0,
        0.0,
        1,
        1.0,
        -0.24999999999999967,
        0.13471894974051282,
        0.3574888971826148,
        0
      ],
      "faceAngle": 0.0,
      "durationTime_ms": 0,
      "faceCenterY": 13.484515733639995,
      "faceCenterX": 0.0,
      "rightEye": [
        -8.768091442516308,
        0.3150672186280232,
        1.523923691978759,
        1.1498237963898936,
        0.0,
        0.6135706948847219,
        0.6135838475596688,
        0.6016947878991474,
        0.6693059490906942,
        0.7149114834914213,
        0.7539830563801151,
        0.6125110795183254,
        0.6383859136636614,
        0.0029779884008463986,
        0.0011604000701112213,
        0.0,
        0.0,
        0.0,
        0.0,
        1,
        1.0,
        -0.24999999999999967,
        -0.14627972230370334,
        0.360255177535185,
        0
      ],
      "triggerTime_ms": 264
    },
    {
      "Name": "ProceduralFaceKeyFrame",
      "faceScaleY": 1.1805843985106215,
      "scanlineOpacity": 1.0,
      "faceScaleX": 0.9419083799034556,
      "leftEye": [
        10.02529858064645,
        0.0,
        1.539480462971507,
        1.1618849354576621,
        0.0,
        0.6135706818949752,
        0.6135838345699222,
        0.6016947878954625,
        0.6693059490870092,
        0.7199306692377064,
        0.7592781113907912,
        0.5817201931442944,
        0.5959217846588241,
        0.0030968562943969324,
        0.0,
        0.0,
        0.0,
        0.0,
        0.0,
        1,
        1.0,
        -0.24999999999999967,
        0.16922782189853924,
        0.39226654134902716,
        0
      ],
      "faceAngle": 0.0,
      "durationTime_ms": 0,
      "faceCenterY": 9.98871829530826,
      "faceCenterX": 0.0,
      "rightEye": [
        -9.299931048500845,
        0.3150672186280232,
        1.523923691978759,
        1.1498237963898936,
        0.0,
        0.6135706948847219,
        0.6135838475596688,
        0.6016947878991474,
        0.6693059490906942,
        0.7199306692377064,
        0.7592781113907912,
        0.5817202048827046,
        0.5959217960185758,
        0.0029442081018168365,
        0.0011604000701112213,
        0.0,
        0.0,
        0.0,
        0.0,
        1,
        1.0,
        -0.24999999999999967,
        -0.18374993897339342,
        0.3957414170048119,
        0
      ],
      "triggerTime_ms": 297
    },
    {
      "Name": "ProceduralFaceKeyFrame",
      "faceScaleY": 1.151411209824712,
      "scanlineOpacity": 1.0,
      "faceScaleX": 0.9552558139104177,
      "leftEye": [
        10.759336738736216,
        0.0,
        1.539480462971507,
        1.1618849354576621,
        0.0,
        0.6135706818949752,
        0.6135838345699222,
        0.6016947878954625,
        0.6693059490870092,
        0.7199306692377064,
        0.7592781113907912,
        0.5817201931442944,
        0.5959217846588241,
        0.00304646273354936,
        0.0,
        0.0,
        0.0,
        0.0,
        0.0,
        1,
        1.0,
        -0.24999999999999967,
        0.2049090512571292,
        0.4282256736084272,
        0
      ],
      "faceAngle": 0.0,
      "durationTime_ms": 0,
      "faceCenterY": 8.771674450171147,
      "faceCenterX": 0.0,
      "rightEye": [
        -9.829785557266348,
        0.3150672186280232,
        1.523923691978759,
        1.1498237963898936,
        0.0,
        0.6135706948847219,
        0.6135838475596688,
        0.6016947878991474,
        0.6693059490906942,
        0.7199306692377064,
        0.7592781113907912,
        0.5817202048827046,
        0.5959217960185758,
        0.002893814540969375,
        0.0011604000701112213,
        0.0,
        0.0,
        0.0,
        0.0,
        1,
        1.0,
        -0.24999999999999967,
        -0.22249311750976597,
        0.43243321741461194,
        0
      ],
      "triggerTime_ms": 330
    },
    {
      "Name": "ProceduralFaceKeyFrame",
      "faceScaleY": 1.0391083904440406,
      "scanlineOpacity": 1.0,
      "faceScaleX": 0.9834337301473387,
      "leftEye": [
        11.067159192128699,
        0.0,
        1.539480462971507,
        1.1618849354576621,
        0.0,
        0.6135706818949752,
        0.6135838345699222,
        0.6016947878954625,
        0.6693059490870092,
        0.7199306692377064,
        0.7592781113907912,
        0.5817201931442944,
        0.5959217846588241,
        0.002976133258520419,
        0.0,
        0.0,
        0.0,
        0.0,
        0.0,
        1,
        1.0,
        -0.24999999999999967,
        0.2405809928832796,
        0.46417544579797554,
        0
      ],
      "faceAngle": 0.0,
      "durationTime_ms": 0,
      "faceCenterY": 8.031210773991106,
      "faceCenterX": 0.0,
      "rightEye": [
        -10.350490041855082,
        0.3150672186280232,
        1.523923691978759,
        1.1498237963898936,
        0.0,
        0.6135706948847219,
        0.6135838475596688,
        0.6016947878991474,
        0.6693059490906942,
        0.7199306692377064,
        0.7592781113907912,
        0.5817202048827046,
        0.5959217960185758,
        0.0028234850659403232,
        0.0011604000701112213,
        0.0,
        0.0,
        0.0,
        0.0,
        1,
        1.0,
        -0.24999999999999967,
        -0.2612262112961854,
        0.4691154670429212,
        0
      ],
      "triggerTime_ms": 363
    },
    {
      "Name": "ProceduralFaceKeyFrame",
      "faceScaleY": 0.9675663056212199,
      "scanlineOpacity": 1.0,
      "faceScaleX": 1.0113891891508089,
      "leftEye": [
        11.06715886516124,
        0.0,
        1.539480462971507,
        1.1618849354576621,
        0.0,
        0.6135706818949752,
        0.6135838345699222,
        0.6016947878954625,
        0.6693059490870092,
        0.7199306692377064,
        0.7592781113907912,
        0.5817201931442944,
        0.5959217846588241,
        0.0003345199117833486,
        0.0,
        0.0,
        0.0,
        0.0,
        0.0,
        1,
        1.0,
        -0.24999999999999967,
        0.26943789948102553,
        0.49325710412642354,
        0
      ],
      "faceAngle": 0.0,
      "durationTime_ms": 0,
      "faceCenterY": 7.448194994996584,
      "faceCenterX": 0.0,
      "rightEye": [
        -10.809563627807755,
        0.3150672186280232,
        1.523923691978759,
        1.1498237963898936,
        0.0,
        0.6135706948847219,
        0.6135838475596688,
        0.6016947878991474,
        0.6693059490906942,
        0.7199306692377064,
        0.7592781113907912,
        0.5817202048827046,
        0.5959217960185758,
        0.00018187171920336365,
        0.0011604000701112213,
        0.0,
        0.0,
        0.0,
        0.0,
        1,
        1.0,
        -0.24999999999999967,
        -0.2925594446074067,
        0.49878966483156406,
        0
      ],
      "triggerTime_ms": 396
    },
    {
      "Name": "ProceduralFaceKeyFrame",
      "faceScaleY": 0.948983461172624,
      "scanlineOpacity": 1.0,
      "faceScaleX": 1.0273319575480147,
      "leftEye": [
        11.067158537027986,
        0.0,
        1.539480462971507,
        1.1618849354576621,
        0.0,
        0.6135706818949752,
        0.6135838345699222,
        0.6016947878954625,
        0.6693059490870092,
        0.7199306692377064,
        0.7592781113907912,
        0.5817201931442944,
        0.5959217846588241,
        0.0003345199117833486,
        0.0,
        0.0,
        0.0,
        0.0,
        0.0,
        1,
        1.0,
        -0.24999999999999967,
        0.26943789948102553,
        0.49325710412642354,
        0
      ],
      "faceAngle": 0.0,
      "durationTime_ms": 0,
      "faceCenterY": 7.766664735774242,
      "faceCenterX": 0.0,
      "rightEye": [
        -11.099077725577274,
        0.3150672186280232,
        1.523923691978759,
        1.1498237963898936,
        0.0,
        0.6135706948847219,
        0.6135838475596688,
        0.6016947878991474,
        0.6693059490906942,
        0.7199306692377064,
        0.7592781113907912,
        0.5817202048827046,
        0.5959217960185758,
        0.00018187171920336365,
        0.0011604000701112213,
        0.0,
        0.0,
        0.0,
        0.0,
        1,
        1.0,
        -0.24999999999999967,
        -0.2925594446074067,
        0.49878966483156406,
        0
      ],
      "triggerTime_ms": 429
    },
    {
      "Name": "ProceduralFaceKeyFrame",
      "faceScaleY": 0.9540102938556996,
      "scanlineOpacity": 1.0,
      "faceScaleX": 1.0233471108066066,
      "leftEye": [
        11.067158208115863,
        0.0,
        1.539480462971507,
        1.1618849354576621,
        0.0,
        0.6135706818949752,
        0.6135838345699222,
        0.6016947878954625,
        0.6693059490870092,
        0.7199306692377064,
        0.7592781113907912,
        0.5817201931442944,
        0.5959217846588241,
        0.0003345199117692488,
        0.0,
        0.0,
        0.0,
        0.0,
        0.0,
        1,
        1.0,
        -0.24999999999999967,
        0.26943789948102553,
        0.49325710412642354,
        0
      ],
      "faceAngle": 0.0,
      "durationTime_ms": 0,
      "faceCenterY": 7.7924089416195415,
      "faceCenterX": 0.0,
      "rightEye": [
        -11.281463593368272,
        0.315067221491347,
        1.5239236875829127,
        1.1498237963899363,
        0.0,
        0.6135706948847219,
        0.6135838475596688,
        0.6016947878991474,
        0.6693059490906942,
        0.7199306692377064,
        0.7592781113907912,
        0.5817202048827046,
        0.5959217960185758,
        0.0001818717191911512,
        0.0011604000700095136,
        0.0,
        0.0,
        0.0,
        0.0,
        1,
        1.0,
        -0.24999999999999967,
        -0.2925594446074067,
        0.49878966483156406,
        0
      ],
      "triggerTime_ms": 462
    },
    {
      "Name": "ProceduralFaceKeyFrame",
      "faceScaleY": 0.9540102938556996,
      "scanlineOpacity": 1.0,
      "faceScaleX": 1.0233471108066066,
      "leftEye": [
        11.067158208115863,
        0.0,
        1.539480462971507,
        1.1618849354576621,
        0.0,
        0.6135706818949752,
        0.6135838345699222,
        0.6016947878954625,
        0.6693059490870092,
        0.7199306692377064,
        0.7592781113907912,
        0.5817201931442944,
        0.5959217846588241,
        0.0003345199117692488,
        0.0,
        0.0,
        0.0,
        0.0,
        0.0,
        1,
        1.0,
        -0.24999999999999967,
        0.26943789948102553,
        0.49325710412642354,
        0
      ],
      "faceAngle": 0.0,
      "durationTime_ms": 0,
      "faceCenterY": 7.7924089416195415,
      "faceCenterX": 0.0,
      "rightEye": [
        -11.281463593368272,
        0.315067221491347,
        1.5239236875829127,
        1.1498237963899363,
        0.0,
        0.6135706948847219,
        0.6135838475596688,
        0.6016947878991474,
        0.6693059490906942,
        0.7199306692377064,
        0.7592781113907912,
        0.5817202048827046,
        0.5959217960185758,
        0.0001818717191911512,
        0.0011604000700095136,
        0.0,
        0.0,
        0.0,
        0.0,
        1,
        1.0,
        -0.24999999999999967,
        -0.2925594446074067,
        0.49878966483156406,
        0
      ],
      "triggerTime_ms": 528
    },
    {
      "Name": "ProceduralFaceKeyFrame",
      "faceScaleY": 0.9540102938556996,
      "scanlineOpacity": 1.0,
      "faceScaleX": 1.0233471108066066,
      "leftEye": [
        11.067158208115863,
        0.0,
        1.539480462971507,
        1.1618849354576621,
        0.0,
        0.6135706818949752,
        0.6135838345699222,
        0.6016947878954625,
        0.6693059490870092,
        0.7199306692377064,
        0.7592781113907912,
        0.5817201931442944,
        0.5959217846588241,
        0.0003345199117692488,
        0.0,
        0.0,
        0.0,
        0.0,
        0.0,
        1,
        1.0,
        -0.24999999999999967,
        0.26943789948102553,
        0.49325710412642354,
        0
      ],
      "faceAngle": 0.0,
      "durationTime_ms": 0,
      "faceCenterY": 7.7924089416195415,
      "faceCenterX": 0.0,
      "rightEye": [
        -11.281463593368272,
        0.315067221491347,
        1.5239236875829127,
        1.1498237963899363,
        0.0,
        0.6135706948847219,
        0.6135838475596688,
        0.6016947878991474,
        0.6693059490906942,
        0.7199306692377064,
        0.7592781113907912,
        0.5817202048827046,
        0.5959217960185758,
        0.0001818717191911512,
        0.0011604000700095136,
        0.0,
        0.0,
        0.0,
        0.0,
        1,
        1.0,
        -0.24999999999999967,
        -0.2925594446074067,
        0.49878966483156406,
        0
      ],
      "triggerTime_ms": 594
    },
    {
      "Name": "ProceduralFaceKeyFrame",
      "faceScaleY": 0.9540102938556996,
      "scanlineOpacity": 1.0,
      "faceScaleX": 1.0233471108066066,
      "leftEye": [
        11.601432102598068,
        0.3862123909395123,
        1.5249862532272869,
        1.1509565594276205,
        0.0,
        0.6135706818949752,
        0.6135838345699222,
        0.6016947878954625,
        0.6693059490870092,
        0.7199306692377064,
        0.7592781113907912,
        0.5817201931442944,
        0.5959217846588241,
        0.0003345199117692488,
        0.0,
        0.0,
        0.0,
        0.0,
        0.0,
        1,
        1.0,
        -0.24999999999999967,
        0.28846877101785856,
        0.49325710412642354,
        0
      ],
      "faceAngle": 0.0,
      "durationTime_ms": 0,
      "faceCenterY": 7.7924089416195415,
      "faceCenterX": 4.338592713243412,
      "rightEye": [
        -11.281463593368258,
        0.04922923495690412,
        1.5291581174962283,
        1.166032036493227,
        0.0,
        0.6135706948847219,
        0.6135838475596688,
        0.6016947878991474,
        0.6693059490906942,
        0.7199306692377064,
        0.7592781113907912,
        0.5817202048827046,
        0.5959217960185758,
        0.0001818717191911512,
        0.0011604000700095136,
        0.0,
        0.0,
        0.0,
        0.0,
        1,
        1.0,
        -0.24999999999999967,
        -0.27333429891081085,
        0.49878966483156406,
        0
      ],
      "triggerTime_ms": 627
    },
    {
      "Name": "ProceduralFaceKeyFrame",
      "faceScaleY": 0.9540102938556996,
      "scanlineOpacity": 1.0,
      "faceScaleX": 1.0233471108066066,
      "leftEye": [
        11.700371712687364,
        0.4577332040764617,
        1.522302140311691,
        1.1489327860887237,
        0.0,
        0.6135706818949752,
        0.6135838345699222,
        0.6016947878954625,
        0.6693059490870092,
        0.7199306692377064,
        0.7592781113907912,
        0.5817201931442944,
        0.5959217846588241,
        0.0003345199117692488,
        0.0,
        0.0,
        0.0,
        0.0,
        0.0,
        1,
        1.0,
        -0.24999999999999967,
        0.2919930064876425,
        0.49325710412642354,
        0
      ],
      "faceAngle": 0.0,
      "durationTime_ms": 0,
      "faceCenterY": 7.7924089416195415,
      "faceCenterX": 5.142032147821565,
      "rightEye": [
        -11.281463593368258,
        -2.18087308212489e-08,
        1.532174275401303,
        1.1690335624382808,
        0.0,
        0.6135706948847219,
        0.6135838475596688,
        0.6016947878991474,
        0.6693059490906942,
        0.7199306692377064,
        0.7592781113907912,
        0.5817202048827046,
        0.5959217960185758,
        0.0001818717191911512,
        0.0011604000700095136,
        0.0,
        0.0,
        0.0,
        0.0,
        1,
        1.0,
        -0.24999999999999967,
        -0.26977408674477465,
        0.49878966483156406,
        0
      ],
      "triggerTime_ms": 660
    },
    {
      "Name": "ProceduralFaceKeyFrame",
      "faceScaleY": 0.9540102938556996,
      "scanlineOpacity": 1.0,
      "faceScaleX": 1.0233471108066066,
      "leftEye": [
        11.700371712687364,
        0.4577332040764617,
        1.522302140311691,
        1.1489327860887237,
        0.0,
        0.6135706818949752,
        0.6135838345699222,
        0.6016947878954625,
        0.6693059490870092,
        0.7199306692377064,
        0.7592781113907912,
        0.5817201931442944,
        0.5959217846588241,
        0.0003345199117692488,
        0.0,
        0.0,
        0.0,
        0.0,
        0.0,
        1,
        1.0,
        -0.24999999999999967,
        0.2919930064876425,
        0.49325710412642354,
        0
      ],
      "faceAngle": 0.0,
      "durationTime_ms": 0,
      "faceCenterY": 7.7924089416195415,
      "faceCenterX": 5.142032147821565,
      "rightEye": [
        -11.281463593368258,
        -2.18087308212489e-08,
        1.532174275401303,
        1.1690335624382808,
        0.0,
        0.6135706948847219,
        0.6135838475596688,
        0.6016947878991474,
        0.6693059490906942,
        0.7199306692377064,
        0.7592781113907912,
        0.5817202048827046,
        0.5959217960185758,
        0.0001818717191911512,
        0.0011604000700095136,
        0.0,
        0.0,
        0.0,
        0.0,
        1,
        1.0,
        -0.24999999999999967,
        -0.26977408674477465,
        0.49878966483156406,
        0
      ],
      "triggerTime_ms": 792
    },
    {
      "Name": "ProceduralFaceKeyFrame",
      "faceScaleY": 0.9540102938556996,
      "scanlineOpacity": 1.0,
      "faceScaleX": 1.0410345914143735,
      "leftEye": [
        11.700371712687364,
        0.4577332040764617,
        1.5354578375856367,
        1.1489327860887237,
        0.0,
        0.6135706818949752,
        0.6135838345699222,
        0.6016947878954625,
        0.6693059490870092,
        0.7199306692377064,
        0.7592781113907912,
        0.5817201931442944,
        0.5959217846588241,
        0.1179917721967233,
        0.0,
        0.0,
        0.0,
        0.0,
        0.0,
        1,
        1.0,
        -0.24999999999999967,
        0.25912484667804814,
        0.5686306619508158,
        0
      ],
      "faceAngle": 0.0,
      "durationTime_ms": 0,
      "faceCenterY": 6.507066730321746,
      "faceCenterX": 5.142032147821565,
      "rightEye": [
        -11.281463593368258,
        -2.18087308212489e-08,
        1.5454152874214135,
        1.1690335624382808,
        0.0,
        0.6135706948847219,
        0.6135838475596688,
        0.6016947878991474,
        0.6693059490906942,
        0.7199306692377064,
        0.7592781113907912,
        0.5817202048827046,
        0.5959217960185758,
        0.11857517137401374,
        0.0011604000700095136,
        0.0,
        0.0,
        0.0,
        0.0,
        1,
        1.0,
        -0.24999999999999967,
        -0.2920322343117696,
        0.5727288550657348,
        0
      ],
      "triggerTime_ms": 825
    },
    {
      "Name": "ProceduralFaceKeyFrame",
      "faceScaleY": 0.9540102938556996,
      "scanlineOpacity": 1.0,
      "faceScaleX": 1.0915702502937081,
      "leftEye": [
        11.700371712687364,
        4.16251906080511,
        1.5730455440826254,
        1.1489327860887237,
        0.0,
        0.6135706818949752,
        0.6135838345699222,
        0.6016947878954625,
        0.6693059490870092,
        0.7199306692377064,
        0.7592781113907912,
        0.5817201931442944,
        0.5959217846588241,
        0.275326065361275,
        0.0,
        0.0,
        0.0,
        0.0,
        0.0,
        1,
        1.0,
        -0.24999999999999967,
        0.16521581865063592,
        0.7839836843062222,
        0
      ],
      "faceAngle": 0.0,
      "durationTime_ms": 0,
      "faceCenterY": 2.8346604123280272,
      "faceCenterX": 5.142032147821565,
      "rightEye": [
        -11.281463593368258,
        3.7047858349199245,
        1.5832467503360146,
        1.1690335624382808,
        0.0,
        0.6135706948847219,
        0.6135838475596688,
        0.6016947878991474,
        0.6693059490906942,
        0.7199306692377064,
        0.7592781113907912,
        0.5817202048827046,
        0.5959217960185758,
        0.28400311997326466,
        0.0011604000700095136,
        0.0,
        0.0,
        0.0,
        0.0,
        1,
        1.0,
        -0.24999999999999967,
        -0.3556269416460408,
        0.7839836843062222,
        0
      ],
      "triggerTime_ms": 858
    },
    {
      "Name": "ProceduralFaceKeyFrame",
      "faceScaleY": 1.0547568722634344,
      "scanlineOpacity": 1.0,
      "faceScaleX": 1.057458680550157,
      "leftEye": [
        12.990873758794798,
        -6.239966744742915,
        1.4623992236907633,
        1.36937574987585,
        0.0,
        0.6,
        0.6,
        0.01,
        0.01,
        0.01,
        0.01,
        0.6,
        0.6,
        0.19378136183743133,
        0.0,
        0.0,
        0.0,
        0.0,
        0.0,
        1,
        1.0,
        0.0,
        0.16521581865063592,
        0.7839836843062222,
        0
      ],
      "faceAngle": 0.0,
      "durationTime_ms": 0,
      "faceCenterY": 2.8346604123280272,
      "faceCenterX": 5.142032147821565,
      "rightEye": [
        -11.28666129765412,
        -6.701836104062167,
        1.5642603023515096,
        1.4180195885823417,
        0.0,
        0.6,
        0.6,
        0.01,
        0.01,
        0.01,
        0.01,
        0.6,
        0.6,
        0.19261138651708598,
        0.0,
        0.0,
        0.0,
        0.0,
        0.0,
        1,
        1.0,
        0.0,
        -0.3556269416460408,
        0.7839836843062222,
        0
      ],
      "triggerTime_ms": 924
    },
    {
      "Name": "ProceduralFaceKeyFrame",
      "faceScaleY": 1.0547568722634344,
      "scanlineOpacity": 1.0,
      "faceScaleX": 1.0617989919075446,
      "leftEye": [
        12.990873758794798,
        1.8022365801324014,
        1.4786481036638524,
        1.0806663196041895,
        0.0,
        0.6,
        0.6,
        0.01,
        0.01,
        0.01,
        0.01,
        0.6,
        0.6,
        0.19378136183743133,
        0.0,
        0.0,
        0.0,
        0.0,
        0.0,
        1,
        1.0,
        0.0,
        0.16521581865063592,
        0.7839836843062222,
        0
      ],
      "faceAngle": 0.0,
      "durationTime_ms": 0,
      "faceCenterY": 2.8346604123280272,
      "faceCenterX": 5.142032147821565,
      "rightEye": [
        -11.28666129765412,
        1.3403672208132065,
        1.581640972067287,
        1.1188643398856721,
        0.0,
        0.6,
        0.6,
        0.01,
        0.01,
        0.01,
        0.01,
        0.6,
        0.6,
        0.19261138651708598,
        0.0,
        0.0,
        0.0,
        0.0,
        0.0,
        1,
        1.0,
        0.0,
        -0.3556269416460408,
        0.7839836843062222,
        0
      ],
      "triggerTime_ms": 990
    },
    {
      "Name": "ProceduralFaceKeyFrame",
      "faceScaleY": 1.0547568722634344,
      "scanlineOpacity": 1.0,
      "faceScaleX": 1.0617989919075446,
      "leftEye": [
        12.990873758794798,
        0.46186935931923756,
        1.4623992236907633,
        1.1308766553036276,
        0.0,
        0.6,
        0.6,
        0.01,
        0.01,
        0.01,
        0.01,
        0.6,
        0.6,
        0.19378136183743133,
        0.0,
        0.0,
        0.0,
        0.0,
        0.0,
        1,
        1.0,
        0.0,
        0.16521581865063592,
        0.7839836843062222,
        0
      ],
      "faceAngle": 0.0,
      "durationTime_ms": 0,
      "faceCenterY": 2.8346604123280272,
      "faceCenterX": 5.142032147821565,
      "rightEye": [
        -11.28666129765412,
        0.0,
        1.5642603023515096,
        1.1708913396590255,
        0.0,
        0.6,
        0.6,
        0.01,
        0.01,
        0.01,
        0.01,
        0.6,
        0.6,
        0.19261138651708598,
        0.0,
        0.0,
        0.0,
        0.0,
        0.0,
        1,
        1.0,
        0.0,
        -0.3556269416460408,
        0.7839836843062222,
        0
      ],
      "triggerTime_ms": 1056
    },
    {
      "Name": "ProceduralFaceKeyFrame",
      "faceScaleY": 1.0547568722634344,
      "scanlineOpacity": 1.0,
      "faceScaleX": 1.0617989919075446,
      "leftEye": [
        12.990873758794798,
        0.46186935931923756,
        1.4623992236907633,
        1.1308766553036276,
        0.0,
        0.6,
        0.6,
        0.01,
        0.01,
        0.01,
        0.01,
        0.6,
        0.6,
        0.19378136183743133,
        0.0,
        0.0,
        0.0,
        0.0,
        0.0,
        1,
        1.0,
        0.0,
        0.16521581865063592,
        0.7839836843062222,
        0
      ],
      "faceAngle": 0.0,
      "durationTime_ms": 0,
      "faceCenterY": 2.8346604123280272,
      "faceCenterX": 5.142032147821565,
      "rightEye": [
        -11.28666129765412,
        0.0,
        1.5642603023515096,
        1.1708913396590255,
        0.0,
        0.6,
        0.6,
        0.01,
        0.01,
        0.01,
        0.01,
        0.6,
        0.6,
        0.19261138651708598,
        0.0,
        0.0,
        0.0,
        0.0,
        0.0,
        1,
        1.0,
        0.0,
        -0.3556269416460408,
        0.7839836843062222,
        0
      ],
      "triggerTime_ms": 1122
    },
    {
      "Name": "ProceduralFaceKeyFrame",
      "faceScaleY": 0.8977033787711309,
      "scanlineOpacity": 1.0,
      "faceScaleX": 1.057687392350144,
      "leftEye": [
        12.648383314886566,
        0.34212606199274376,
        1.5300269067446108,
        1.1308766553036276,
        0.0,
        0.6000000000000005,
        0.6000000000000005,
        0.16296296306163563,
        0.16296296306163563,
        0.15658377633043186,
        0.15995408387131652,
        0.6000000000000005,
        0.6000000000000005,
        0.19378136183743133,
        0.0,
        0.0,
        0.0,
        0.0,
        0.0,
        1,
        1.0,
        0.0,
        0.18226737516554742,
        0.7623285346541695,
        0
      ],
      "faceAngle": 0.0,
      "durationTime_ms": 0,
      "faceCenterY": 8.32920717134268,
      "faceCenterX": 5.11924388412871,
      "rightEye": [
        -10.931173156482991,
        -6.106444629949692e-07,
        1.5616600805732888,
        1.164163490655636,
        0.0,
        0.6157993854922783,
        0.6157993854922783,
        0.17876234855391332,
        0.17876234855391332,
        0.17876234855391332,
        0.17876234855391332,
        0.6157993854922783,
        0.6157993854922783,
        0.1926287139495203,
        0.00038057140256939314,
        0.0,
        0.0,
        0.0,
        0.0,
        1,
        1.0,
        0.0,
        -0.32796424243608946,
        0.7591437879734144,
        0
      ],
      "triggerTime_ms": 1188
    },
    {
      "Name": "ProceduralFaceKeyFrame",
      "faceScaleY": 0.4489791116502639,
      "scanlineOpacity": 1.0,
      "faceScaleX": 1.0459399650432852,
      "leftEye": [
        11.669839189434484,
        2.3553456145464224e-06,
        1.723248858327032,
        1.1308766553036276,
        0.0,
        0.6000000000000022,
        0.6000000000000022,
        0.6000000000000022,
        0.6000000000000022,
        0.6000000000000022,
        0.6000000000000022,
        0.6000000000000022,
        0.6000000000000022,
        0.19378136183743133,
        0.0,
        0.0,
        0.0,
        0.0,
        0.0,
        1,
        1.0,
        0.0,
        0.23098610806529452,
        0.7004566785054476,
        0
      ],
      "faceAngle": 0.0,
      "durationTime_ms": 0,
      "faceCenterY": 24.02791219709882,
      "faceCenterX": 5.05413455439077,
      "rightEye": [
        -9.915492753136917,
        -2.3553429358003086e-06,
        1.5507888734988744,
        1.144941064931666,
        0.0,
        0.6609404868987877,
        0.6609404868987877,
        0.6609404868987877,
        0.6609404868987877,
        0.6609404868987877,
        0.6609404868987877,
        0.6609404868987877,
        0.6609404868987877,
        0.1930792271928099,
        0.010275427869373617,
        0.0,
        0.0,
        0.0,
        0.0,
        1,
        1.0,
        0.0,
        -0.2489279589790856,
        0.6881726555939636,
        0
      ],
      "triggerTime_ms": 1221
    },
    {
      "Name": "ProceduralFaceKeyFrame",
      "faceScaleY": 0.9370933470029604,
      "scanlineOpacity": 1.0,
      "faceScaleX": 1.0912124881131013,
      "leftEye": [
        12.648383314886544,
        0.3460517129937628,
        1.5470230165150345,
        1.1308766553036276,
        0.0,
        0.6000000000000005,
        0.6000000000000005,
        0.6000000000000005,
        0.6000000000000005,
        0.6287063402904193,
        0.6135399563564381,
        0.6000000000000005,
        0.6000000000000005,
        0.36006323659905737,
        0.0,
        0.0,
        0.0,
        0.0,
        0.0,
        1,
        1.0,
        0.0,
        0.16521581865063592,
        0.7839836843062222,
        0
      ],
      "faceAngle": 0.0,
      "durationTime_ms": 0,
      "faceCenterY": 8.221337090539848,
      "faceCenterX": 5.142032147821565,
      "rightEye": [
        -10.95400822335884,
        -6.106444629949692e-07,
        1.5401662883950213,
        1.1552146235714615,
        0.0,
        0.6157993854922784,
        0.6157993854922784,
        0.6157993854922784,
        0.6157993854922784,
        0.644505725782697,
        0.6293393418487159,
        0.6157993854922784,
        0.6157993854922784,
        0.34573837274734875,
        0.2877119803424492,
        0.0,
        0.0,
        0.0,
        0.0,
        1,
        1.0,
        0.0,
        -0.3556269416460408,
        0.7839836843062222,
        0
      ],
      "triggerTime_ms": 1287
    },
    {
      "Name": "ProceduralFaceKeyFrame",
      "faceScaleY": 1.175096148771853,
      "scanlineOpacity": 1.0,
      "faceScaleX": 1.0617989919075446,
      "leftEye": [
        12.978641957226642,
        0.4577332040764617,
        1.4641389766060764,
        1.1308766553036276,
        0.0,
        0.6000000000000001,
        0.6000000000000001,
        0.6000000000000001,
        0.6000000000000001,
        0.6383947301384352,
        0.6181096916267352,
        0.6000000000000001,
        0.6000000000000001,
        0.3726106466298911,
        0.0,
        0.0,
        0.0,
        0.0,
        0.0,
        1,
        1.0,
        0.0,
        0.16521581865063592,
        0.7839836843062222,
        0
      ],
      "faceAngle": 0.0,
      "durationTime_ms": 0,
      "faceCenterY": 6.039472338147277,
      "faceCenterX": 5.142032147821565,
      "rightEye": [
        -11.281463593368258,
        -2.18087308212489e-08,
        1.547832789330906,
        1.1586819496123923,
        0.0,
        0.6005642637675813,
        0.6005642637675813,
        0.6005642637675813,
        0.6005642637675813,
        0.6389589939060165,
        0.6186739553943167,
        0.6005642637675813,
        0.6005642637675813,
        0.3659178490359096,
        0.010275427869373617,
        0.0,
        0.0,
        0.0,
        0.0,
        1,
        1.0,
        0.0,
        -0.3556269416460408,
        0.7839836843062222,
        0
      ],
      "triggerTime_ms": 1353
    },
    {
      "Name": "ProceduralFaceKeyFrame",
      "faceScaleY": 1.0547568722634344,
      "scanlineOpacity": 1.0,
      "faceScaleX": 1.0591254584273446,
      "leftEye": [
        12.990873758794798,
        0.46186935931923756,
        1.4623992236907633,
        1.1308766553036276,
        0.0,
        0.6,
        0.6,
        0.6,
        0.6,
        0.6387535593920654,
        0.6182789410811907,
        0.6,
        0.6,
        0.3726106466298911,
        0.0,
        0.0,
        0.0,
        0.0,
        0.0,
        1,
        1.0,
        0.0,
        0.16521581865063592,
        0.7839836843062222,
        0
      ],
      "faceAngle": 0.0,
      "durationTime_ms": 0,
      "faceCenterY": 5.958662532503098,
      "faceCenterX": 5.142032147821565,
      "rightEye": [
        -11.28666129765412,
        0.0,
        1.5642603023515096,
        1.1708913396590255,
        0.0,
        0.6,
        0.6,
        0.6,
        0.6,
        0.6387535593920654,
        0.6182789410811907,
        0.6,
        0.6,
        0.3654500083601858,
        0.0,
        0.0,
        0.0,
        0.0,
        0.0,
        1,
        1.0,
        0.0,
        -0.3556269416460408,
        0.7839836843062222,
        0
      ],
      "triggerTime_ms": 1419
    },
    {
      "Name": "ProceduralFaceKeyFrame",
      "faceScaleY": 1.0547568722634344,
      "scanlineOpacity": 1.0,
      "faceScaleX": 1.0591254584273446,
      "leftEye": [
        12.990873758794798,
        0.46186935931923756,
        1.4623992236907633,
        1.1308766553036276,
        0.0,
        0.6,
        0.6,
        0.6,
        0.6,
        0.6387535593920654,
        0.6182789410811907,
        0.6,
        0.6,
        0.3726106466298911,
        0.0,
        0.0,
        0.0,
        0.0,
        0.0,
        1,
        1.0,
        0.0,
        0.16521581865063592,
        0.7839836843062222,
        0
      ],
      "faceAngle": 0.0,
      "durationTime_ms": 0,
      "faceCenterY": 5.958662532503098,
      "faceCenterX": 5.142032147821565,
      "rightEye": [
        -11.28666129765412,
        0.0,
        1.5642603023515096,
        1.1708913396590255,
        0.0,
        0.6,
        0.6,
        0.6,
        0.6,
        0.6387535593920654,
        0.6182789410811907,
        0.6,
        0.6,
        0.3654500083601858,
        0.0,
        0.0,
        0.0,
        0.0,
        0.0,
        1,
        1.0,
        0.0,
        -0.3556269416460408,
        0.7839836843062222,
        0
      ],
      "triggerTime_ms": 1452
    },
    {
      "Name": "ProceduralFaceKeyFrame",
      "faceScaleY": 0.8882201264823768,
      "scanlineOpacity": 1.0,
      "faceScaleX": 1.0892158767940432,
      "leftEye": [
        12.990873758794798,
        0.46186935931923756,
        1.4623992236907633,
        1.1308766553036276,
        0.0,
        0.6,
        0.6,
        0.6,
        0.6,
        0.6387535593920654,
        0.6182789410811907,
        0.6,
        0.6,
        0.3726106466298911,
        0.0,
        0.0,
        0.0,
        0.0,
        0.0,
        1,
        1.0,
        0.0,
        0.16521581865063592,
        0.7839836843062222,
        0
      ],
      "faceAngle": 0.0,
      "durationTime_ms": 0,
      "faceCenterY": 7.904375607938881,
      "faceCenterX": 5.142032147821565,
      "rightEye": [
        -11.28666129765412,
        0.0,
        1.5642603023515096,
        1.1708913396590255,
        0.0,
        0.6,
        0.6,
        0.6,
        0.6,
        0.6387535593920654,
        0.6182789410811907,
        0.6,
        0.6,
        0.3654500083601858,
        0.0,
        0.0,
        0.0,
        0.0,
        0.0,
        1,
        1.0,
        0.0,
        -0.3556269416460408,
        0.7839836843062222,
        0
      ],
      "triggerTime_ms": 1518
    },
    {
      "Name": "ProceduralFaceKeyFrame",
      "faceScaleY": 0.9930248230815159,
      "scanlineOpacity": 1.0,
      "faceScaleX": 0.9675795558744553,
      "leftEye": [
        12.990873758794798,
        0.46186935931923756,
        1.4623992236907633,
        1.1308766553036276,
        0.0,
        0.6,
        0.6,
        0.6,
        0.6,
        0.6387535593920654,
        0.6182789410811907,
        0.6,
        0.6,
        0.3726106466298911,
        0.0,
        0.0,
        0.0,
        0.0,
        0.0,
        1,
        1.0,
        0.0,
        0.16521581865063592,
        0.7839836843062222,
        0
      ],
      "faceAngle": 0.0,
      "durationTime_ms": 0,
      "faceCenterY": 4.543903757047097,
      "faceCenterX": 5.142032147821565,
      "rightEye": [
        -11.28666129765412,
        0.0,
        1.5642603023515096,
        1.1708913396590255,
        0.0,
        0.6,
        0.6,
        0.6,
        0.6,
        0.6387535593920654,
        0.6182789410811907,
        0.6,
        0.6,
        0.3654500083601858,
        0.0,
        0.0,
        0.0,
        0.0,
        0.0,
        1,
        1.0,
        0.0,
        -0.3556269416460408,
        0.7839836843062222,
        0
      ],
      "triggerTime_ms": 1584
    },
    {
      "Name": "ProceduralFaceKeyFrame",
      "faceScaleY": 0.8867950617780669,
      "scanlineOpacity": 1.0,
      "faceScaleX": 1.1114373747031956,
      "leftEye": [
        12.990873758794798,
        0.46186935931923756,
        1.4623992236907633,
        1.1308766553036276,
        0.0,
        0.6,
        0.6,
        0.6,
        0.6,
        0.6387535593920654,
        0.6182789410811907,
        0.6,
        0.6,
        0.3726106466298911,
        0.0,
        0.0,
        0.0,
        0.0,
        0.0,
        1,
        1.0,
        0.0,
        0.16521581865063592,
        0.7839836843062222,
        0
      ],
      "faceAngle": 0.0,
      "durationTime_ms": 0,
      "faceCenterY": 7.9500690737846895,
      "faceCenterX": 5.142032147821565,
      "rightEye": [
        -11.28666129765412,
        0.0,
        1.5642603023515096,
        1.1708913396590255,
        0.0,
        0.6,
        0.6,
        0.6,
        0.6,
        0.6387535593920654,
        0.6182789410811907,
        0.6,
        0.6,
        0.3654500083601858,
        0.0,
        0.0,
        0.0,
        0.0,
        0.0,
        1,
        1.0,
        0.0,
        -0.3556269416460408,
        0.7839836843062222,
        0
      ],
      "triggerTime_ms": 1650
    },
    {
      "Name": "ProceduralFaceKeyFrame",
      "faceScaleY": 0.9925291922396495,
      "scanlineOpacity": 1.0,
      "faceScaleX": 0.947187262932549,
      "leftEye": [
        12.990873758794798,
        0.46186935931923756,
        1.4623992236907633,
        1.1308766553036276,
        0.0,
        0.6,
        0.6,
        0.01,
        0.01,
        0.01,
        0.01,
        0.6,
        0.6,
        0.3726106466298911,
        0.0,
        0.0,
        0.0,
        0.0,
        0.0,
        1,
        1.0,
        0.0,
        0.16521581865063592,
        0.7839836843062222,
        0
      ],
      "faceAngle": 0.0,
      "durationTime_ms": 0,
      "faceCenterY": 4.559795730847625,
      "faceCenterX": 5.142032147821565,
      "rightEye": [
        -11.28666129765412,
        0.0,
        1.5642603023515096,
        1.1708913396590255,
        0.0,
        0.6,
        0.6,
        0.01,
        0.01,
        0.01,
        0.01,
        0.6,
        0.6,
        0.3654500083601858,
        0.0,
        0.0,
        0.0,
        0.0,
        0.0,
        1,
        1.0,
        0.0,
        -0.3556269416460408,
        0.7839836843062222,
        0
      ],
      "triggerTime_ms": 1716
    },
    {
      "Name": "ProceduralFaceKeyFrame",
      "faceScaleY": 0.9305855546346935,
      "scanlineOpacity": 1.0,
      "faceScaleX": 1.090739734976299,
      "leftEye": [
        12.990873758794798,
        0.46186935931923756,
        1.4623992236907633,
        1.1308766553036276,
        0.0,
        0.6,
        0.6,
        0.01,
        0.01,
        0.01,
        0.01,
        0.6,
        0.6,
        0.3726106466298911,
        0.0,
        0.0,
        0.0,
        0.0,
        0.0,
        1,
        1.0,
        0.0,
        0.16521581865063592,
        0.7839836843062222,
        0
      ],
      "faceAngle": 0.0,
      "durationTime_ms": 0,
      "faceCenterY": 6.545964836507785,
      "faceCenterX": 5.142032147821565,
      "rightEye": [
        -11.28666129765412,
        0.0,
        1.5642603023515096,
        1.1708913396590255,
        0.0,
        0.6,
        0.6,
        0.01,
        0.01,
        0.01,
        0.01,
        0.6,
        0.6,
        0.3654500083601858,
        0.0,
        0.0,
        0.0,
        0.0,
        0.0,
        1,
        1.0,
        0.0,
        -0.3556269416460408,
        0.7839836843062222,
        0
      ],
      "triggerTime_ms": 1815
    },
    {
      "Name": "ProceduralFaceKeyFrame",
      "faceScaleY": 1.0431327785289637,
      "scanlineOpacity": 1.0,
      "faceScaleX": 1.0485188780696533,
      "leftEye": [
        12.990873758794798,
        0.46186935931923756,
        1.4623992236907633,
        1.1308766553036276,
        0.0,
        0.6,
        0.6,
        0.01,
        0.01,
        0.01,
        0.01,
        0.6,
        0.6,
        0.3726106466298911,
        0.0,
        0.0,
        0.0,
        0.0,
        0.0,
        1,
        1.0,
        0.0,
        0.16521581865063592,
        0.7839836843062222,
        0
      ],
      "faceAngle": 0.0,
      "durationTime_ms": 0,
      "faceCenterY": 5.497918402749846,
      "faceCenterX": 5.142032147821565,
      "rightEye": [
        -11.28666129765412,
        0.0,
        1.5642603023515096,
        1.1708913396590255,
        0.0,
        0.6,
        0.6,
        0.01,
        0.01,
        0.01,
        0.01,
        0.6,
        0.6,
        0.3654500083601858,
        0.0,
        0.0,
        0.0,
        0.0,
        0.0,
        1,
        1.0,
        0.0,
        -0.3556269416460408,
        0.7839836843062222,
        0
      ],
      "triggerTime_ms": 1914
    },
    {
      "Name": "ProceduralFaceKeyFrame",
      "faceScaleY": 1.0547568722634344,
      "scanlineOpacity": 1.0,
      "faceScaleX": 1.0591254584273446,
      "leftEye": [
        12.990873758794798,
        0.46186935931923756,
        1.4623992236907633,
        1.1308766553036276,
        0.0,
        0.6,
        0.6,
        0.01,
        0.01,
        0.01,
        0.01,
        0.6,
        0.6,
        0.3726106466298911,
        0.0,
        0.0,
        0.0,
        0.0,
        0.0,
        1,
        1.0,
        0.0,
        0.16521581865063592,
        0.7839836843062222,
        0
      ],
      "faceAngle": 0.0,
      "durationTime_ms": 0,
      "faceCenterY": 5.958662532503098,
      "faceCenterX": 5.142032147821565,
      "rightEye": [
        -11.28666129765412,
        0.0,
        1.5642603023515096,
        1.1708913396590255,
        0.0,
        0.6,
        0.6,
        0.01,
        0.01,
        0.01,
        0.01,
        0.6,
        0.6,
        0.3654500083601858,
        0.0,
        0.0,
        0.0,
        0.0,
        0.0,
        1,
        1.0,
        0.0,
        -0.3556269416460408,
        0.7839836843062222,
        0
      ],
      "triggerTime_ms": 1980
    },
    {
      "Name": "ProceduralFaceKeyFrame",
      "faceScaleY": 1.0547568722634344,
      "scanlineOpacity": 1.0,
      "faceScaleX": 1.0591254584273446,
      "leftEye": [
        12.990873758794798,
        0.46186935931923756,
        1.4623992236907633,
        1.1308766553036276,
        0.0,
        0.6,
        0.6,
        0.01,
        0.01,
        0.01,
        0.01,
        0.6,
        0.6,
        0.3726106466298911,
        0.0,
        0.0,
        0.0,
        0.0,
        0.0,
        1,
        1.0,
        0.0,
        0.16521581865063592,
        0.7839836843062222,
        0
      ],
      "faceAngle": 0.0,
      "durationTime_ms": 0,
      "faceCenterY": 5.958662532503098,
      "faceCenterX": 5.142032147821565,
      "rightEye": [
        -11.28666129765412,
        0.0,
        1.5642603023515096,
        1.1708913396590255,
        0.0,
        0.6,
        0.6,
        0.01,
        0.01,
        0.01,
        0.01,
        0.6,
        0.6,
        0.3654500083601858,
        0.0,
        0.0,
        0.0,
        0.0,
        0.0,
        1,
        1.0,
        0.0,
        -0.3556269416460408,
        0.7839836843062222,
        0
      ],
      "triggerTime_ms": 2277
    },
    {
      "Name": "ProceduralFaceKeyFrame",
      "faceScaleY": 1.0561049746268352,
      "scanlineOpacity": 1.0,
      "faceScaleX": 1.060386434963997,
      "leftEye": [
        12.889970306630026,
        1.4122936233371775,
        1.4797892468184837,
        1.1001705703339864,
        0.0,
        0.6010610821234754,
        0.601062110521928,
        0.01,
        0.01,
        0.01,
        0.01,
        0.5985707146902947,
        0.5996811271955459,
        0.498079402238779,
        0.0,
        0.0,
        0.0,
        0.0,
        0.0,
        1,
        1.0,
        -0.019547325102880434,
        0.054583384407759936,
        0.7213868972149464,
        0
      ],
      "faceAngle": 0.0,
      "durationTime_ms": 0,
      "faceCenterY": 5.970386192010636,
      "faceCenterX": 4.9679138004576116,
      "rightEye": [
        -11.295649488542274,
        1.1330084570904972,
        1.569020772719922,
        1.1318095572165063,
        0.0,
        0.6010610831391345,
        0.6010621115375872,
        0.01,
        0.01,
        0.01,
        0.01,
        0.5985707156081127,
        0.599681128083757,
        0.49730720186330946,
        9.073086967152487e-05,
        0.0,
        0.0,
        0.0,
        0.0,
        1,
        1.0,
        -0.019547325102880434,
        -0.30554812969835654,
        0.6383790448012479,
        0
      ],
      "triggerTime_ms": 2310
    },
    {
      "Name": "ProceduralFaceKeyFrame",
      "faceScaleY": 1.0599566956651238,
      "scanlineOpacity": 1.0,
      "faceScaleX": 1.0639892250687186,
      "leftEye": [
        12.345622735741074,
        4.127791520531339,
        1.5541079038822248,
        1.0124388989921527,
        0.0,
        0.6067853409474876,
        0.6067919172849611,
        0.01,
        0.01,
        0.01,
        0.01,
        0.5908600965721471,
        0.597960892329412,
        0.2599294068629955,
        0.0,
        0.0,
        0.0,
        0.0,
        0.0,
        1,
        1.0,
        -0.12500000000000044,
        -0.08316679839027363,
        0.49000812494370316,
        0
      ],
      "faceAngle": 0.0,
      "durationTime_ms": 0,
      "faceCenterY": 6.275201339206532,
      "faceCenterX": 4.028590235092754,
      "rightEye": [
        -11.344138413070453,
        4.370175477349129,
        1.5826221166296717,
        1.0201473216664492,
        0.0,
        0.6067853474423609,
        0.6067919237798344,
        0.01,
        0.01,
        0.01,
        0.01,
        0.5908601024413522,
        0.5979608980092879,
        0.2600151585729019,
        0.0005802000350047597,
        0.0,
        0.0,
        0.0,
        0.0,
        1,
        1.0,
        -0.12500000000000044,
        -0.2554693177506724,
        0.4927744052962735,
        0
      ],
      "triggerTime_ms": 2343
    },
    {
      "Name": "ProceduralFaceKeyFrame",
      "faceScaleY": 0.9814778795099947,
      "scanlineOpacity": 1.0,
      "faceScaleX": 1.033883955244932,
      "leftEye": [
        11.795964456843471,
        0.3477911139486025,
        1.5773526482852749,
        1.1447908037475405,
        0.0,
        0.6125654461990512,
        0.6125776246017798,
        0.01,
        0.01,
        0.01,
        0.01,
        0.5830742529113837,
        0.5962238746840963,
        0.18674148092466036,
        0.0,
        0.0,
        0.0,
        0.0,
        0.0,
        1,
        1.0,
        -0.2314814814814813,
        -0.10124529742704547,
        0.49313677156410063,
        0
      ],
      "faceAngle": 0.0,
      "durationTime_ms": 0,
      "faceCenterY": 8.645334502979772,
      "faceCenterX": 3.0801009744808825,
      "rightEye": [
        -11.393100400276957,
        1.1118441938308479,
        1.5452533453493986,
        1.13043342594188,
        0.0,
        0.6125654582265943,
        0.612577636629323,
        0.01,
        0.01,
        0.01,
        0.01,
        0.5830742637802819,
        0.596223885202385,
        0.1870077046462013,
        0.0010744445092680688,
        0.0,
        0.0,
        0.0,
        0.0,
        1,
        1.0,
        -0.2314814814814813,
        -0.3111219808116743,
        0.4985668774413682,
        0
      ],
      "triggerTime_ms": 2376
    },
    {
      "Name": "ProceduralFaceKeyFrame",
      "faceScaleY": 0.9540102938556996,
      "scanlineOpacity": 1.0,
      "faceScaleX": 1.0233471108066066,
      "leftEye": [
        11.700371712687364,
        -0.9752090283553585,
        1.5782466769161616,
        1.1911139704119265,
        0.0,
        0.6135706818949752,
        0.6135838345699222,
        0.01,
        0.01,
        0.01,
        0.01,
        0.5817201931442944,
        0.5959217846588241,
        0.18671533323775924,
        0.0,
        0.0,
        0.0,
        0.0,
        0.0,
        1,
        1.0,
        -0.24999999999999967,
        -0.10194062431307516,
        0.49325710412642354,
        0
      ],
      "faceAngle": 0.0,
      "durationTime_ms": 0,
      "faceCenterY": 9.229563535105243,
      "faceCenterX": 2.915146158232786,
      "rightEye": [
        -11.401615528486786,
        -0.028571755400548682,
        1.532174275401303,
        1.1690335624382808,
        0.0,
        0.6135706948847219,
        0.6135838475596688,
        0.01,
        0.01,
        0.01,
        0.01,
        0.5817202048827046,
        0.5959217960185758,
        0.18698399397042575,
        0.0011604000700095136,
        0.0,
        0.0,
        0.0,
        0.0,
        1,
        1.0,
        -0.24999999999999967,
        -0.3132624678524819,
        0.49878966483156406,
        0
      ],
      "triggerTime_ms": 2409
    },
    {
      "Name": "ProceduralFaceKeyFrame",
      "faceScaleY": 0.9540102938556996,
      "scanlineOpacity": 1.0,
      "faceScaleX": 1.0233471108066066,
      "leftEye": [
        11.700371712687364,
        -0.9752090283553585,
        1.5782466769161616,
        1.1911139704119265,
        0.0,
        0.6135706818949752,
        0.6135838345699222,
        0.01,
        0.01,
        0.01,
        0.01,
        0.5817201931442944,
        0.5959217846588241,
        0.18671533323775924,
        0.0,
        0.0,
        0.0,
        0.0,
        0.0,
        1,
        1.0,
        -0.24999999999999967,
        -0.10194062431307516,
        0.49325710412642354,
        0
      ],
      "faceAngle": 0.0,
      "durationTime_ms": 0,
      "faceCenterY": 9.229563535105243,
      "faceCenterX": 2.915146158232786,
      "rightEye": [
        -11.401615528486786,
        -0.028571755400548682,
        1.532174275401303,
        1.1690335624382808,
        0.0,
        0.6135706948847219,
        0.6135838475596688,
        0.01,
        0.01,
        0.01,
        0.01,
        0.5817202048827046,
        0.5959217960185758,
        0.18698399397042575,
        0.0011604000700095136,
        0.0,
        0.0,
        0.0,
        0.0,
        1,
        1.0,
        -0.24999999999999967,
        -0.3132624678524819,
        0.49878966483156406,
        0
      ],
      "triggerTime_ms": 2574
    },
    {
      "Name": "ProceduralFaceKeyFrame",
      "faceScaleY": 1.039015219387226,
      "scanlineOpacity": 1.0,
      "faceScaleX": 1.0535350916116042,
      "leftEye": [
        12.78923281409051,
        0.2373258612450826,
        1.4805003882572316,
        1.1402887357892992,
        0.0,
        0.6021204190460899,
        0.6021224741515503,
        0.01,
        0.01,
        0.01,
        0.01,
        0.597143780178796,
        0.5993627788529412,
        0.15587841622591203,
        0.0,
        0.0,
        0.0,
        0.0,
        0.0,
        1,
        1.0,
        -0.03906249999999972,
        0.12347262443755626,
        0.637161070164492,
        0
      ],
      "faceAngle": 0.0,
      "durationTime_ms": 0,
      "faceCenterY": 6.469740814159678,
      "faceCenterX": 4.794081780028107,
      "rightEye": [
        -11.304622896221723,
        -0.004464336781332179,
        1.5592468606405396,
        1.1706010619682843,
        0.0,
        0.6021204210757378,
        0.6021224761811983,
        0.01,
        0.01,
        0.01,
        0.01,
        0.5971437820129225,
        0.5993627806279025,
        0.1560498299681372,
        0.00018131251093898544,
        0.0,
        0.0,
        0.0,
        0.0,
        1,
        1.0,
        -0.03906249999999972,
        0.08523136976923806,
        0.637161070164492,
        0
      ],
      "triggerTime_ms": 2607
    },
    {
      "Name": "ProceduralFaceKeyFrame",
      "faceScaleY": 1.0547568722634344,
      "scanlineOpacity": 1.0,
      "faceScaleX": 1.0591254584273446,
      "leftEye": [
        12.990873758794798,
        0.46186935931923756,
        1.4623992236907633,
        1.1308766553036276,
        0.0,
        0.6,
        0.6,
        0.01,
        0.01,
        0.01,
        0.01,
        0.6,
        0.6,
        0.09531020838467086,
        0.0,
        0.0,
        0.0,
        0.0,
        0.0,
        1,
        1.0,
        0.0,
        0.16521581865063592,
        0.6620844195427202,
        0
      ],
      "faceAngle": 0.0,
      "durationTime_ms": 0,
      "faceCenterY": 5.958662532503098,
      "faceCenterX": 5.142032147821565,
      "rightEye": [
        -11.28666129765412,
        0.0,
        1.5642603023515096,
        1.1708913396590255,
        0.0,
        0.6,
        0.6,
        0.01,
        0.01,
        0.01,
        0.01,
        0.6,
        0.6,
        0.09557434277062105,
        0.0,
        0.0,
        0.0,
        0.0,
        0.0,
        1,
        1.0,
        0.0,
        0.15902652488437077,
        0.6620844195427202,
        0
      ],
      "triggerTime_ms": 2640
    },
    {
      "Name": "ProceduralFaceKeyFrame",
      "faceScaleY": 1.0547568722634344,
      "scanlineOpacity": 1.0,
      "faceScaleX": 1.0591254584273446,
      "leftEye": [
        12.990873758794798,
        0.46186935931923756,
        1.4623992236907633,
        1.1308766553036276,
        0.0,
        0.6,
        0.6,
        0.01,
        0.01,
        0.01,
        0.01,
        0.6,
        0.6,
        0.0953592046613877,
        0.0,
        0.0,
        0.0,
        0.0,
        0.0,
        1,
        1.0,
        0.0,
        0.16521581865063592,
        0.6620844195427202,
        0
      ],
      "faceAngle": 0.0,
      "durationTime_ms": 0,
      "faceCenterY": 5.958662532503098,
      "faceCenterX": 5.142032147821565,
      "rightEye": [
        -11.28666129765412,
        0.0,
        1.5642603023515096,
        1.1708913396590255,
        0.0,
        0.6,
        0.6,
        0.01,
        0.01,
        0.01,
        0.01,
        0.6,
        0.6,
        0.09557434277062105,
        0.0,
        0.0,
        0.0,
        0.0,
        0.0,
        1,
        1.0,
        0.0,
        0.15902652488437077,
        0.6620844195427202,
        0
      ],
      "triggerTime_ms": 3168
    },
    {
      "Name": "ProceduralFaceKeyFrame",
      "faceScaleY": 1.0509845377193927,
      "scanlineOpacity": 1.0,
      "faceScaleX": 1.0470338174293634,
      "leftEye": [
        12.996351387317304,
        0.46186935931923756,
        1.4623992236907633,
        1.1308766553036276,
        0.0,
        0.5917893468586057,
        0.5917893468586057,
        0.01,
        0.01,
        0.01,
        0.01,
        0.5917893468586057,
        0.5917893468586057,
        0.047726207643802865,
        0.0,
        0.0,
        0.0,
        0.0,
        0.0,
        1,
        1.0,
        -0.018391927083331837,
        0.13484724889148297,
        0.6574112915343027,
        0
      ],
      "faceAngle": 0.0,
      "durationTime_ms": 0,
      "faceCenterY": 6.754604316567665,
      "faceCenterX": 5.142032147821565,
      "rightEye": [
        -11.38601126963804,
        5.4200740073895304e-05,
        1.5589884883645142,
        1.1683362741271845,
        0.0,
        0.5917893473049536,
        0.5917893473049536,
        0.01,
        0.01,
        0.01,
        0.01,
        0.5917893473049536,
        0.5917893473049536,
        0.052771712934055026,
        4.2683986953957475e-05,
        0.0,
        0.0,
        0.0,
        0.0,
        1,
        1.0,
        -0.018391927083331837,
        0.12865795512521783,
        0.6574112915343027,
        0
      ],
      "triggerTime_ms": 3201
    },
    {
      "Name": "ProceduralFaceKeyFrame",
      "faceScaleY": 1.0245781959110976,
      "scanlineOpacity": 1.0,
      "faceScaleX": 1.034942176431381,
      "leftEye": [
        13.00182901583981,
        0.46186935931923756,
        1.4623992236907633,
        1.1308766553036276,
        0.0,
        0.5686134554778063,
        0.5686134554778063,
        0.01,
        0.01,
        0.01,
        0.01,
        0.5686134554778063,
        0.5686134554778063,
        8.644124301548928e-05,
        0.0,
        0.0,
        0.0,
        0.0,
        0.0,
        1,
        1.0,
        -0.0781249999999993,
        -0.3617272330819169,
        0.6527381635258847,
        0
      ],
      "faceAngle": 0.0,
      "durationTime_ms": 0,
      "faceCenterY": 9.542446265397146,
      "faceCenterX": 5.142032147821565,
      "rightEye": [
        -11.485361241621973,
        0.00023023323218041014,
        1.5537166743775186,
        1.1628490486117173,
        0.0,
        0.568613456370502,
        0.568613456370502,
        0.01,
        0.01,
        0.01,
        0.01,
        0.568613456370502,
        0.568613456370502,
        0.009969083097485676,
        0.00018131251095487673,
        0.0,
        0.0,
        0.0,
        0.0,
        1,
        1.0,
        -0.0781249999999993,
        -0.37211436636587136,
        0.6527381635258847,
        0
      ],
      "triggerTime_ms": 3234
    },
    {
      "Name": "ProceduralFaceKeyFrame",
      "faceScaleY": 0.5917120909486383,
      "scanlineOpacity": 1.0,
      "faceScaleX": 1.0563565050349861,
      "leftEye": [
        8.56663926933308,
        0.15123794400136603,
        1.6808097719381645,
        1.1308766553036276,
        0.0,
        0.480278094084766,
        0.480278094084766,
        0.01,
        0.01,
        0.01,
        0.01,
        0.480278094084766,
        0.480278094084766,
        7.741539875028014e-05,
        0.0,
        0.0,
        0.0,
        0.0,
        0.0,
        1,
        1.0,
        -0.3307291666666645,
        -0.6074957297756339,
        0.8052714127254357,
        0
      ],
      "faceAngle": 0.0,
      "durationTime_ms": 0,
      "faceCenterY": 21.893863850621393,
      "faceCenterX": -6.064749026705698,
      "rightEye": [
        -8.98887032972928,
        0.00097465401623964,
        1.6280203040729178,
        1.147434059790019,
        0.0,
        0.480278094084766,
        0.480278094084766,
        0.01,
        0.01,
        0.01,
        0.01,
        0.480278094084766,
        0.480278094084766,
        0.042202451779356,
        0.0007675562963756466,
        0.0,
        0.0,
        0.0,
        0.0,
        1,
        1.0,
        -0.3307291666666645,
        -0.6167748526475546,
        0.786344860476244,
        0
      ],
      "triggerTime_ms": 3300
    },
    {
      "Name": "ProceduralFaceKeyFrame",
      "faceScaleY": 0.45679722211466434,
      "scanlineOpacity": 1.0,
      "faceScaleX": 1.1678853060781709,
      "leftEye": [
        9.749335801045618,
        0.0,
        1.7360454624641861,
        1.1452821488839107,
        0.0,
        0.5086184552324969,
        0.5086184552324969,
        0.6000024416090023,
        0.6000024416090023,
        0.5999992546316143,
        0.5999992546316143,
        0.5086184552324969,
        0.5086184552324969,
        6.754732048575018e-05,
        0.0,
        0.0,
        0.0,
        0.0,
        0.0,
        1,
        1.0,
        -0.5,
        -0.547149510430738,
        0.7406374898936465,
        0
      ],
      "faceAngle": 0.0,
      "durationTime_ms": 0,
      "faceCenterY": 25.35617864912738,
      "faceCenterX": -6.847578205837451,
      "rightEye": [
        -10.188709366319486,
        0.0014734926859674147,
        1.5174494071053928,
        1.1449400548293385,
        0.0,
        0.5086184662304092,
        0.5086184662304092,
        0.6000024416126871,
        0.6000024416126871,
        0.5999992546316143,
        0.5999992546316143,
        0.5086184662304092,
        0.5086184662304092,
        0.06380213182390859,
        0.0011604000701112213,
        0.0,
        0.0,
        0.0,
        0.0,
        1,
        1.0,
        -0.5,
        -0.6091373344293362,
        0.7406256760741324,
        0
      ],
      "triggerTime_ms": 3333
    },
    {
      "Name": "ProceduralFaceKeyFrame",
      "faceScaleY": 0.9223206929047992,
      "scanlineOpacity": 1.0,
      "faceScaleX": 1.0148109203574596,
      "leftEye": [
        10.097438406055723,
        0.0,
        1.690354921634933,
        1.1452821488839107,
        0.0,
        0.564287633942715,
        0.564287633942715,
        0.6000024416090023,
        0.6000024416090023,
        0.5999992546316143,
        0.5999992546316143,
        0.564287633942715,
        0.564287633942715,
        5.7195589517999856e-05,
        0.0,
        0.0,
        0.0,
        0.0,
        0.0,
        1,
        1.0,
        -0.5,
        -0.40564734813376413,
        0.31478510792848235,
        0
      ],
      "faceAngle": 0.0,
      "durationTime_ms": 0,
      "faceCenterY": 11.169764305297619,
      "faceCenterX": -6.083637379447836,
      "rightEye": [
        -11.583004748115016,
        0.0014734926859674147,
        1.5174494071053928,
        1.1449400548293385,
        0.0,
        0.5642876470190232,
        0.5642876470190232,
        0.6000024416126871,
        0.6000024416126871,
        0.5999992546316143,
        0.5999992546316143,
        0.5642876470190232,
        0.5642876470190232,
        0.03190106591195396,
        0.0011604000701112213,
        0.0,
        0.0,
        0.0,
        0.0,
        1,
        1.0,
        -0.5,
        -0.43400904073021707,
        0.3147780251107103,
        0
      ],
      "triggerTime_ms": 3366
    },
    {
      "Name": "ProceduralFaceKeyFrame",
      "faceScaleY": 1.0759241457981688,
      "scanlineOpacity": 1.0,
      "faceScaleX": 0.9525505028810533,
      "leftEye": [
        9.86355111179342,
        0.0,
        1.617341321282393,
        1.1452821488839107,
        0.0,
        0.6000027100003369,
        0.6000027100003369,
        0.6000024416090023,
        0.6000024416090023,
        0.5999992546316143,
        0.5999992546316143,
        0.6000027100003369,
        0.6000027100003369,
        4.671878714335165e-05,
        0.0,
        0.0,
        0.0,
        0.0,
        0.0,
        1,
        1.0,
        -0.5,
        -0.3122908369136972,
        0.12225257862834982,
        0
      ],
      "faceAngle": 0.0,
      "durationTime_ms": 0,
      "faceCenterY": 3.877460980254014,
      "faceCenterX": -3.510370323179359,
      "rightEye": [
        -9.340032189735886,
        0.0014734926859674147,
        1.5174494071053928,
        1.1449400548293385,
        0.0,
        0.6000027229900835,
        0.6000027229900835,
        0.6000024416126871,
        0.6000024416126871,
        0.5999992546316143,
        0.5999992546316143,
        0.6000027229900835,
        0.6000027229900835,
        0.0,
        0.0011604000701112213,
        0.0,
        0.0,
        0.0,
        0.0,
        1,
        1.0,
        -0.5,
        -0.3328485763237742,
        0.12224982788597105,
        0
      ],
      "triggerTime_ms": 3399
    },
    {
      "Name": "ProceduralFaceKeyFrame",
      "faceScaleY": 1.0924991089307012,
      "scanlineOpacity": 1.0,
      "faceScaleX": 0.945610075107667,
      "leftEye": [
        8.344740057208803,
        0.0,
        1.517460986277885,
        1.1452821488839107,
        0.0,
        0.6000027100003369,
        0.6000027100003369,
        0.6000024416090023,
        0.6000024416090023,
        0.5999992546316143,
        0.5999992546316143,
        0.6000027100003369,
        0.6000027100003369,
        2.6824293357430307e-05,
        0.0,
        0.0,
        0.0,
        0.0,
        0.0,
        1,
        1.0,
        -0.5,
        -0.2536277180920746,
        -0.011554394812550137,
        0
      ],
      "faceAngle": 0.0,
      "durationTime_ms": 0,
      "faceCenterY": 1.0524834639262508,
      "faceCenterX": -0.3036296709257158,
      "rightEye": [
        -7.822116038681841,
        0.0014734926859674147,
        1.5174494071053928,
        1.1449400548293385,
        0.0,
        0.6000027229900835,
        0.6000027229900835,
        0.6000024416126871,
        0.6000024416126871,
        0.5999992546316143,
        0.5999992546316143,
        0.6000027229900835,
        0.6000027229900835,
        0.0,
        0.0011604000701112213,
        0.0,
        0.0,
        0.0,
        0.0,
        1,
        1.0,
        -0.5,
        -0.25362965344430644,
        -0.011554134833056623,
        0
      ],
      "triggerTime_ms": 3498
    },
    {
      "Name": "ProceduralFaceKeyFrame",
      "faceScaleY": 1.0088250033255441,
      "scanlineOpacity": 1.0,
      "faceScaleX": 0.9948108552222862,
      "leftEye": [
        8.147088816155147,
        0.0,
        1.5174508121161652,
        1.1453061203864572,
        0.0,
        0.600000281840035,
        0.600000281840035,
        0.6000002539273362,
        0.6000002539273362,
        0.5999999224816879,
        0.5999999224816879,
        0.600000281840035,
        0.600000281840035,
        1.0732489497233821e-05,
        0.0,
        0.0,
        0.0,
        0.0,
        0.0,
        1,
        1.0,
        -0.05200000000000077,
        -0.05075485504409161,
        -0.012512478899502692,
        0
      ],
      "faceAngle": 0.0,
      "durationTime_ms": 0,
      "faceCenterY": 0.009649827819970369,
      "faceCenterX": 0.0,
      "rightEye": [
        -7.349791600809247,
        0.00015324323933896267,
        1.5174505924785215,
        1.1449409598810238,
        0.0,
        0.6000002831909687,
        0.6000002831909687,
        0.6000002539277194,
        0.6000002539277194,
        0.5999999224816879,
        0.5999999224816879,
        0.6000002831909687,
        0.6000002831909687,
        0.0,
        0.00012068160729156879,
        0.0,
        0.0,
        0.0,
        0.0,
        1,
        1.0,
        -0.05200000000000077,
        -0.05075486239041116,
        -0.01251244961969337,
        0
      ],
      "triggerTime_ms": 3564
    },
    {
      "Name": "ProceduralFaceKeyFrame",
      "faceScaleY": 1.0,
      "scanlineOpacity": 1.0,
      "faceScaleX": 1.0,
      "leftEye": [
        8.107326060759803,
        0.0,
        1.5174507300664741,
        1.1453089027930028,
        0.0,
        0.6,
        0.6,
        0.6,
        0.6,
        0.6,
        0.6,
        0.6,
        0.6,
        0.0,
        0.0,
        0.0,
        0.0,
        0.0,
        0.0,
        1,
        1.0,
        0.0,
        0.0,
        0.0,
        0
      ],
      "faceAngle": 0.0,
      "durationTime_ms": 0,
      "faceCenterY": 0.0,
      "faceCenterX": 0.0,
      "rightEye": [
        -7.315991464547729,
        0.0,
        1.5174507300664741,
        1.144941064931666,
        0.0,
        0.6,
        0.6,
        0.6,
        0.6,
        0.6,
        0.6,
        0.6,
        0.6,
        0.0,
        0.0,
        0.0,
        0.0,
        0.0,
        0.0,
        1,
        1.0,
        0.0,
        0.0,
        0.0,
        0
      ],
      "triggerTime_ms": 3663
    },
    {
      "eventGroups": [
        {
          "probabilities": [
            0.5,
            0.5
          ],
          "audioName": [
            "Play__Robot_Vic_Sfx__Head_Down_Micro_Curious",
            "Play__Robot_Vic_Sfx__Lift_High_Dancing_Small"
          ],
          "eventIds": [
            16087513,
            992178953
          ],
          "volumes": [
            1.0,
            1.0
          ]
        }
      ],
      "triggerTime_ms": 198,
      "Name": "RobotAudioKeyFrame"
    },
    {
      "eventGroups": [
        {
          "probabilities": [
            1.0
          ],
          "audioName": [
            "Play__Robot_Vic_Sfx__Scrn_Angry"
          ],
          "eventIds": [
            2459769158
          ],
          "volumes": [
            1.0
          ]
        }
      ],
      "triggerTime_ms": 792,
      "Name": "RobotAudioKeyFrame"
    },
    {
      "eventGroups": [
        {
          "probabilities": [
            1.0
          ],
          "audioName": [
            "Play__Robot_Vic_Sfx__Emote_Feedback_Shut_Up_Come_At_Me"
          ],
          "eventIds": [
            1181334695
          ],
          "volumes": [
            1.0
          ]
        }
      ],
      "triggerTime_ms": 858,
      "Name": "RobotAudioKeyFrame"
    },
    {
      "eventGroups": [
        {
          "probabilities": [
            1.0
          ],
          "audioName": [
            "Play__Robot_Vic_Sfx__Lift_High_Down_Long_Angry"
          ],
          "eventIds": [
            1827504806
          ],
          "volumes": [
            1.0
          ]
        }
      ],
      "triggerTime_ms": 1122,
      "Name": "RobotAudioKeyFrame"
    },
    {
      "eventGroups": [
        {
          "probabilities": [
            1.0
          ],
          "audioName": [
            "Play__Robot_Vic_Sfx__Scrn_Angry"
          ],
          "eventIds": [
            2459769158
          ],
          "volumes": [
            1.0
          ]
        }
      ],
      "triggerTime_ms": 2277,
      "Name": "RobotAudioKeyFrame"
    },
    {
      "eventGroups": [
        {
          "probabilities": [
            0.5
          ],
          "audioName": [
            "Play__Robot_Vic_Sfx__Head_Down_Micro_Curious"
          ],
          "eventIds": [
            16087513
          ],
          "volumes": [
            1.0
          ]
        }
      ],
      "triggerTime_ms": 3267,
      "Name": "RobotAudioKeyFrame"
    },
    {
      "Right": [
        0.0,
        0.0,
        0.0,
        0.0
      ],
      "Name": "BackpackLightsKeyFrame",
      "durationTime_ms": 99,
      "Back": [
        0.0,
        0.0,
        0.0,
        0.0
      ],
      "Middle": [
        0.0,
        0.0,
        0.0,
        0.0
      ],
      "Front": [
        0.0,
        0.0,
        0.0,
        0.0
      ],
      "triggerTime_ms": 0,
      "Left": [
        0.0,
        0.0,
        0.0,
        0.0
      ]
    },
    {
      "Right": [
        0.0,
        0.0,
        0.0,
        0.0
      ],
      "Name": "BackpackLightsKeyFrame",
      "durationTime_ms": 33,
      "Back": [
        0.0,
        0.0,
        0.0,
        0.0
      ],
      "Middle": [
        0.0,
        0.0,
        0.0,
        0.0
      ],
      "Front": [
        0.0,
        0.0,
        0.0,
        0.0
      ],
      "triggerTime_ms": 99,
      "Left": [
        0.0,
        0.0,
        0.0,
        0.0
      ]
    },
    {
      "Right": [
        0.0,
        0.0,
        0.0,
        0.0
      ],
      "Name": "BackpackLightsKeyFrame",
      "durationTime_ms": 66,
      "Back": [
        0.0,
        0.0,
        0.0,
        0.0
      ],
      "Middle": [
        0.0,
        0.0,
        0.0,
        0.0
      ],
      "Front": [
        0.0,
        0.0,
        0.0,
        0.0
      ],
      "triggerTime_ms": 132,
      "Left": [
        0.0,
        0.0,
        0.0,
        0.0
      ]
    },
    {
      "Right": [
        0.0,
        0.0,
        0.0,
        0.0
      ],
      "Name": "BackpackLightsKeyFrame",
      "durationTime_ms": 33,
      "Back": [
        0.0,
        0.0,
        0.0,
        0.0
      ],
      "Middle": [
        0.0,
        0.0,
        0.0,
        0.0
      ],
      "Front": [
        0.0,
        0.0,
        0.0,
        0.0
      ],
      "triggerTime_ms": 198,
      "Left": [
        0.0,
        0.0,
        0.0,
        0.0
      ]
    },
    {
      "Right": [
        0.0,
        0.0,
        0.0,
        0.0
      ],
      "Name": "BackpackLightsKeyFrame",
      "durationTime_ms": 396,
      "Back": [
        0.0,
        0.0,
        0.0,
        0.0
      ],
      "Middle": [
        0.0,
        0.0,
        0.0,
        0.0
      ],
      "Front": [
        0.0,
        0.0,
        0.0,
        0.0
      ],
      "triggerTime_ms": 231,
      "Left": [
        0.0,
        0.0,
        0.0,
        0.0
      ]
    },
    {
      "Right": [
        0.0,
        0.0,
        0.0,
        0.0
      ],
      "Name": "BackpackLightsKeyFrame",
      "durationTime_ms": 132,
      "Back": [
        0.0,
        0.0,
        0.0,
        0.0
      ],
      "Middle": [
        0.0,
        0.0,
        0.0,
        0.0
      ],
      "Front": [
        0.0,
        0.0,
        0.0,
        0.0
      ],
      "triggerTime_ms": 627,
      "Left": [
        0.0,
        0.0,
        0.0,
        0.0
      ]
    },
    {
      "Right": [
        0.0,
        0.0,
        0.0,
        0.0
      ],
      "Name": "BackpackLightsKeyFrame",
      "durationTime_ms": 231,
      "Back": [
        0.0,
        0.0,
        0.0,
        0.0
      ],
      "Middle": [
        0.0,
        0.0,
        0.0,
        0.0
      ],
      "Front": [
        0.0,
        0.0,
        0.0,
        0.0
      ],
      "triggerTime_ms": 759,
      "Left": [
        0.0,
        0.0,
        0.0,
        0.0
      ]
    },
    {
      "Right": [
        0.0,
        0.0,
        0.0,
        0.0
      ],
      "Name": "BackpackLightsKeyFrame",
      "durationTime_ms": 165,
      "Back": [
        0.0,
        0.0,
        0.0,
        0.0
      ],
      "Middle": [
        0.0,
        0.0,
        0.0,
        0.0
      ],
      "Front": [
        0.0,
        0.0,
        0.0,
        0.0
      ],
      "triggerTime_ms": 990,
      "Left": [
        0.0,
        0.0,
        0.0,
        0.0
      ]
    },
    {
      "Right": [
        0.0,
        0.0,
        0.0,
        0.0
      ],
      "Name": "BackpackLightsKeyFrame",
      "durationTime_ms": 561,
      "Back": [
        0.0,
        0.0,
        0.0,
        0.0
      ],
      "Middle": [
        0.0,
        0.0,
        0.0,
        0.0
      ],
      "Front": [
        0.0,
        0.0,
        0.0,
        0.0
      ],
      "triggerTime_ms": 1155,
      "Left": [
        0.0,
        0.0,
        0.0,
        0.0
      ]
    },
    {
      "Right": [
        0.0,
        0.0,
        0.0,
        0.0
      ],
      "Name": "BackpackLightsKeyFrame",
      "durationTime_ms": 99,
      "Back": [
        0.0,
        0.0,
        0.0,
        0.0
      ],
      "Middle": [
        0.0,
        0.0,
        0.0,
        0.0
      ],
      "Front": [
        0.0,
        0.0,
        0.0,
        0.0
      ],
      "triggerTime_ms": 1716,
      "Left": [
        0.0,
        0.0,
        0.0,
        0.0
      ]
    },
    {
      "Right": [
        0.0,
        0.0,
        0.0,
        0.0
      ],
      "Name": "BackpackLightsKeyFrame",
      "durationTime_ms": 1485,
      "Back": [
        0.0,
        0.0,
        0.0,
        0.0
      ],
      "Middle": [
        0.0,
        0.0,
        0.0,
        0.0
      ],
      "Front": [
        0.0,
        0.0,
        0.0,
        0.0
      ],
      "triggerTime_ms": 1815,
      "Left": [
        0.0,
        0.0,
        0.0,
        0.0
      ]
    },
    {
      "Right": [
        0.0,
        0.0,
        0.0,
        0.0
      ],
      "Name": "BackpackLightsKeyFrame",
      "durationTime_ms": 33,
      "Back": [
        0.0,
        0.0,
        0.0,
        0.0
      ],
      "Middle": [
        0.0,
        0.0,
        0.0,
        0.0
      ],
      "Front": [
        0.0,
        0.0,
        0.0,
        0.0
      ],
      "triggerTime_ms": 3300,
      "Left": [
        0.0,
        0.0,
        0.0,
        0.0
      ]
    },
    {
      "Right": [
        0.0,
        0.0,
        0.0,
        0.0
      ],
      "Name": "BackpackLightsKeyFrame",
      "durationTime_ms": 330,
      "Back": [
        0.0,
        0.0,
        0.0,
        0.0
      ],
      "Middle": [
        0.0,
        0.0,
        0.0,
        0.0
      ],
      "Front": [
        0.0,
        0.0,
        0.0,
        0.0
      ],
      "triggerTime_ms": 3333,
      "Left": [
        0.0,
        0.0,
        0.0,
        0.0
      ]
    },
    {
      "durationTime_ms": 33,
      "speed": 220,
      "triggerTime_ms": 132,
      "Name": "BodyMotionKeyFrame",
      "radius_mm": "STRAIGHT"
    },
    {
      "durationTime_ms": 33,
      "speed": 70,
      "triggerTime_ms": 165,
      "Name": "BodyMotionKeyFrame",
      "radius_mm": "STRAIGHT"
    },
    {
      "durationTime_ms": 231,
      "speed": -82,
      "triggerTime_ms": 198,
      "Name": "BodyMotionKeyFrame",
      "radius_mm": 130
    },
    {
      "durationTime_ms": 66,
      "speed": 64,
      "triggerTime_ms": 429,
      "Name": "BodyMotionKeyFrame",
      "radius_mm": "STRAIGHT"
    },
    {
      "durationTime_ms": 66,
      "speed": -44,
      "triggerTime_ms": 825,
      "Name": "BodyMotionKeyFrame",
      "radius_mm": "STRAIGHT"
    },
    {
      "durationTime_ms": 99,
      "speed": 46,
      "triggerTime_ms": 891,
      "Name": "BodyMotionKeyFrame",
      "radius_mm": "STRAIGHT"
    },
    {
      "durationTime_ms": 66,
      "speed": 131,
      "triggerTime_ms": 1188,
      "Name": "BodyMotionKeyFrame",
      "radius_mm": 28
    },
    {
      "durationTime_ms": 66,
      "speed": -50,
      "triggerTime_ms": 1254,
      "Name": "BodyMotionKeyFrame",
      "radius_mm": 18
    },
    {
      "durationTime_ms": 66,
      "speed": 220,
      "triggerTime_ms": 1320,
      "Name": "BodyMotionKeyFrame",
      "radius_mm": 69
    },
    {
      "durationTime_ms": 66,
      "speed": -19,
      "triggerTime_ms": 1386,
      "Name": "BodyMotionKeyFrame",
      "radius_mm": 5
    },
    {
      "durationTime_ms": 66,
      "speed": 50,
      "triggerTime_ms": 1452,
      "Name": "BodyMotionKeyFrame",
      "radius_mm": 18
    },
    {
      "durationTime_ms": 66,
      "speed": -50,
      "triggerTime_ms": 1518,
      "Name": "BodyMotionKeyFrame",
      "radius_mm": 18
    },
    {
      "durationTime_ms": 66,
      "speed": 26,
      "triggerTime_ms": 1584,
      "Name": "BodyMotionKeyFrame",
      "radius_mm": 15
    },
    {
      "durationTime_ms": 66,
      "speed": 210,
      "triggerTime_ms": 1650,
      "Name": "BodyMotionKeyFrame",
      "radius_mm": -35
    },
    {
      "durationTime_ms": 99,
      "speed": -171,
      "triggerTime_ms": 1716,
      "Name": "BodyMotionKeyFrame",
      "radius_mm": 68
    },
    {
      "durationTime_ms": 66,
      "speed": 35,
      "triggerTime_ms": 2310,
      "Name": "BodyMotionKeyFrame",
      "radius_mm": -28
    },
    {
      "durationTime_ms": 66,
      "speed": -6,
      "triggerTime_ms": 2607,
      "Name": "BodyMotionKeyFrame",
      "radius_mm": -3
    },
    {
      "durationTime_ms": 66,
      "speed": 34,
      "triggerTime_ms": 3234,
      "Name": "BodyMotionKeyFrame",
      "radius_mm": 21
    },
    {
      "durationTime_ms": 165,
      "speed": 58,
      "triggerTime_ms": 3300,
      "Name": "BodyMotionKeyFrame",
      "radius_mm": -9
    },
    {
      "durationTime_ms": 66,
      "speed": -15,
      "triggerTime_ms": 3465,
      "Name": "BodyMotionKeyFrame",
      "radius_mm": -9
    }
  ]
}