{
  "anim_greeting_goodnight_01": [
    {
      "durationTime_ms": 132,
      "triggerTime_ms": 0,
      "Name": "LiftHeightKeyFrame",
      "heightVariability_mm": 0,
      "height_mm": 32
    },
    {
      "durationTime_ms": 66,
      "triggerTime_ms": 660,
      "Name": "LiftHeightKeyFrame",
      "heightVariability_mm": 0,
      "height_mm": 38
    },
    {
      "durationTime_ms": 132,
      "triggerTime_ms": 726,
      "Name": "LiftHeightKeyFrame",
      "heightVariability_mm": 0,
      "height_mm": 32
    },
    {
      "angleVariability_deg": 0,
      "angle_deg": 0,
      "triggerTime_ms": 0,
      "Name": "HeadAngleKeyFrame",
      "durationTime_ms": 99
    },
    {
      "angleVariability_deg": 0,
      "angle_deg": -18,
      "triggerTime_ms": 99,
      "Name": "HeadAngleKeyFrame",
      "durationTime_ms": 99
    },
    {
      "angleVariability_deg": 0,
      "angle_deg": 13,
      "triggerTime_ms": 198,
      "Name": "HeadAngleKeyFrame",
      "durationTime_ms": 132
    },
    {
      "angleVariability_deg": 0,
      "angle_deg": 8,
      "triggerTime_ms": 330,
      "Name": "HeadAngleKeyFrame",
      "durationTime_ms": 99
    },
    {
      "angleVariability_deg": 0,
      "angle_deg": 9,
      "triggerTime_ms": 528,
      "Name": "HeadAngleKeyFrame",
      "durationTime_ms": 165
    },
    {
      "angleVariability_deg": 0,
      "angle_deg": 1,
      "triggerTime_ms": 693,
      "Name": "HeadAngleKeyFrame",
      "durationTime_ms": 99
    },
    {
      "angleVariability_deg": 0,
      "angle_deg": 13,
      "triggerTime_ms": 792,
      "Name": "HeadAngleKeyFrame",
      "durationTime_ms": 132
    },
    {
      "angleVariability_deg": 0,
      "angle_deg": 16,
      "triggerTime_ms": 924,
      "Name": "HeadAngleKeyFrame",
      "durationTime_ms": 99
    },
    {
      "angleVariability_deg": 0,
      "angle_deg": 14,
      "triggerTime_ms": 1023,
      "Name": "HeadAngleKeyFrame",
      "durationTime_ms": 33
    },
    {
      "angleVariability_deg": 0,
      "angle_deg": 17,
      "triggerTime_ms": 1056,
      "Name": "HeadAngleKeyFrame",
      "durationTime_ms": 33
    },
    {
      "angleVariability_deg": 0,
      "angle_deg": 13,
      "triggerTime_ms": 1089,
      "Name": "HeadAngleKeyFrame",
      "durationTime_ms": 33
    },
    {
      "angleVariability_deg": 0,
      "angle_deg": 18,
      "triggerTime_ms": 1122,
      "Name": "HeadAngleKeyFrame",
      "durationTime_ms": 33
    },
    {
      "angleVariability_deg": 0,
      "angle_deg": 14,
      "triggerTime_ms": 1155,
      "Name": "HeadAngleKeyFrame",
      "durationTime_ms": 33
    },
    {
      "angleVariability_deg": 0,
      "angle_deg": 18,
      "triggerTime_ms": 1188,
      "Name": "HeadAngleKeyFrame",
      "durationTime_ms": 33
    },
    {
      "angleVariability_deg": 0,
      "angle_deg": 14,
      "triggerTime_ms": 1221,
      "Name": "HeadAngleKeyFrame",
      "durationTime_ms": 33
    },
    {
      "angleVariability_deg": 0,
      "angle_deg": 19,
      "triggerTime_ms": 1254,
      "Name": "HeadAngleKeyFrame",
      "durationTime_ms": 33
    },
    {
      "angleVariability_deg": 0,
      "angle_deg": 15,
      "triggerTime_ms": 1287,
      "Name": "HeadAngleKeyFrame",
      "durationTime_ms": 33
    },
    {
      "angleVariability_deg": 0,
      "angle_deg": 18,
      "triggerTime_ms": 1320,
      "Name": "HeadAngleKeyFrame",
      "durationTime_ms": 33
    },
    {
      "angleVariability_deg": 0,
      "angle_deg": 15,
      "triggerTime_ms": 1353,
      "Name": "HeadAngleKeyFrame",
      "durationTime_ms": 33
    },
    {
      "angleVariability_deg": 0,
      "angle_deg": 18,
      "triggerTime_ms": 1386,
      "Name": "HeadAngleKeyFrame",
      "durationTime_ms": 33
    },
    {
      "angleVariability_deg": 0,
      "angle_deg": 15,
      "triggerTime_ms": 1419,
      "Name": "HeadAngleKeyFrame",
      "durationTime_ms": 33
    },
    {
      "angleVariability_deg": 0,
      "angle_deg": 18,
      "triggerTime_ms": 1452,
      "Name": "HeadAngleKeyFrame",
      "durationTime_ms": 33
    },
    {
      "angleVariability_deg": 0,
      "angle_deg": 15,
      "triggerTime_ms": 1485,
      "Name": "HeadAngleKeyFrame",
      "durationTime_ms": 33
    },
    {
      "angleVariability_deg": 0,
      "angle_deg": 17,
      "triggerTime_ms": 1518,
      "Name": "HeadAngleKeyFrame",
      "durationTime_ms": 33
    },
    {
      "angleVariability_deg": 0,
      "angle_deg": 19,
      "triggerTime_ms": 1815,
      "Name": "HeadAngleKeyFrame",
      "durationTime_ms": 99
    },
    {
      "angleVariability_deg": 0,
      "angle_deg": -21,
      "triggerTime_ms": 1914,
      "Name": "HeadAngleKeyFrame",
      "durationTime_ms": 99
    },
    {
      "angleVariability_deg": 0,
      "angle_deg": 12,
      "triggerTime_ms": 2013,
      "Name": "HeadAngleKeyFrame",
      "durationTime_ms": 132
    },
    {
      "angleVariability_deg": 0,
      "angle_deg": -3,
      "triggerTime_ms": 2145,
      "Name": "HeadAngleKeyFrame",
      "durationTime_ms": 132
    },
    {
      "angleVariability_deg": 0,
      "angle_deg": 0,
      "triggerTime_ms": 2277,
      "Name": "HeadAngleKeyFrame",
      "durationTime_ms": 132
    },
    {
      "Name": "ProceduralFaceKeyFrame",
      "faceScaleY": 1.0,
      "scanlineOpacity": 1.0,
      "faceScaleX": 1.0,
      "leftEye": [
        8.107326060759803,
        0.0,
        1.5174507300664741,
        1.1453089027930028,
        0.0,
        0.6,
        0.6,
        0.6,
        0.6,
        0.6,
        0.6,
        0.6,
        0.6,
        0.0,
        0.0,
        0.0,
        0.0,
        0.0,
        0.0,
        1,
        1.0,
        0.0,
        0.0,
        0.0,
        0
      ],
      "faceAngle": 0.0,
      "durationTime_ms": 0,
      "faceCenterY": 0.0,
      "faceCenterX": 0.0,
      "rightEye": [
        -7.315991464547729,
        0.0,
        1.5174507300664741,
        1.144941064931666,
        0.0,
        0.6,
        0.6,
        0.6,
        0.6,
        0.6,
        0.6,
        0.6,
        0.6,
        0.0,
        0.0,
        0.0,
        0.0,
        0.0,
        0.0,
        1,
        1.0,
        0.0,
        0.0,
        0.0,
        0
      ],
      "triggerTime_ms": 0
    },
    {
      "Name": "ProceduralFaceKeyFrame",
      "faceScaleY": 1.0,
      "scanlineOpacity": 1.0,
      "faceScaleX": 1.0,
      "leftEye": [
        8.107326060759803,
        0.0,
        1.5174507300664741,
        1.1453089027930028,
        0.0,
        0.6,
        0.6,
        0.6,
        0.6,
        0.6,
        0.6,
        0.6,
        0.6,
        0.0,
        0.0,
        0.0,
        0.0,
        0.0,
        0.0,
        1,
        1.0,
        0.0,
        0.0,
        0.0,
        0
      ],
      "faceAngle": 0.0,
      "durationTime_ms": 0,
      "faceCenterY": 0.0,
      "faceCenterX": 0.0,
      "rightEye": [
        -7.315991464547729,
        0.0,
        1.5174507300664741,
        1.144941064931666,
        0.0,
        0.6,
        0.6,
        0.6,
        0.6,
        0.6,
        0.6,
        0.6,
        0.6,
        0.0,
        0.0,
        0.0,
        0.0,
        0.0,
        0.0,
        1,
        1.0,
        0.0,
        0.0,
        0.0,
        0
      ],
      "triggerTime_ms": 66
    },
    {
      "Name": "ProceduralFaceKeyFrame",
      "faceScaleY": 0.8736820542215372,
      "scanlineOpacity": 1.0,
      "faceScaleX": 1.0135788442683724,
      "leftEye": [
        8.107326060759803,
        0.0,
        1.5175175593287542,
        1.1453592923637432,
        0.0010641449554517216,
        0.5500188683305774,
        0.5500500742803601,
        0.5500188683305774,
        0.5500500742803601,
        0.5500995791142826,
        0.5501345568105724,
        0.5500407598203405,
        0.5500719657701233,
        0.0004826403178380678,
        0.0,
        0.0001193229973091066,
        0.0,
        0.0,
        0.0,
        1,
        1.0,
        0.0003408676147460934,
        -0.08227622595355455,
        0.0487250388175563,
        0
      ],
      "faceAngle": 0.0,
      "durationTime_ms": 0,
      "faceCenterY": 2.2905300004260027,
      "faceCenterX": 1.8997845050648303,
      "rightEye": [
        -9.155158526872107,
        -9.314601489052166e-05,
        1.5134185022916218,
        1.1142724727813405,
        -0.0010640031260904207,
        0.5500188383740299,
        0.550050051877043,
        0.5500188383740299,
        0.550050051877043,
        0.5500995791142826,
        0.5501345568105724,
        0.5500407598203405,
        0.5500719657701233,
        0.0004822388871424943,
        0.0,
        0.0001193229973091066,
        0.0,
        0.0,
        0.0,
        1,
        1.0,
        0.0003408676147460934,
        -0.08273699994671457,
        0.051578828519915576,
        0
      ],
      "triggerTime_ms": 99
    },
    {
      "Name": "ProceduralFaceKeyFrame",
      "faceScaleY": 0.7395506272609017,
      "scanlineOpacity": 1.0,
      "faceScaleX": 1.0279976170481904,
      "leftEye": [
        8.107326060759803,
        0.0,
        1.5175885223598353,
        1.145412798815148,
        0.0021941133102097348,
        0.4969461202692318,
        0.4970104624337323,
        0.4969461202692318,
        0.4970104624337323,
        0.4971125342562531,
        0.4971846532176751,
        0.49699125736152694,
        0.49705559952602746,
        0.0009951346759546897,
        0.0,
        0.0002460267985753974,
        0.0,
        0.0,
        0.0,
        1,
        1.0,
        0.0007028198242187492,
        -0.1696417029970202,
        0.10046399756197222,
        0
      ],
      "faceAngle": 0.0,
      "durationTime_ms": 0,
      "faceCenterY": 4.722742268919589,
      "faceCenterX": 3.1874816658110934,
      "rightEye": [
        -11.108088500268103,
        -0.00019205363895480332,
        1.5091368583657476,
        1.0817068543124384,
        -0.002193820878536949,
        0.4969460585031544,
        0.4970104162413259,
        0.4969460585031544,
        0.4970104162413259,
        0.4971125342562531,
        0.4971846532176751,
        0.49699125736152694,
        0.49705559952602746,
        0.000994306983799098,
        0.0,
        0.0002460267985753974,
        0.0,
        0.0,
        0.0,
        1,
        1.0,
        0.0007028198242187492,
        -0.17059175246745317,
        0.10634810004106343,
        0
      ],
      "triggerTime_ms": 132
    },
    {
      "Name": "ProceduralFaceKeyFrame",
      "faceScaleY": 0.8629607336691703,
      "scanlineOpacity": 1.0,
      "faceScaleX": 1.014844838090002,
      "leftEye": [
        6.130024879713474,
        0.002892868118387071,
        1.5719124867822323,
        0.8653226943391052,
        0.00323631713255936,
        0.5457043257426791,
        0.5458119849954106,
        0.5457043257426791,
        0.5458119849954106,
        0.5459827746513517,
        0.5461034462755464,
        0.5457798504886167,
        0.5458875097413483,
        0.0014678236470330175,
        0.0,
        0.00036288952789882223,
        0.0,
        0.0,
        0.0,
        1,
        1.0,
        0.0010475959777832026,
        -0.09946100791528267,
        0.36735717699077985,
        0
      ],
      "faceAngle": 0.0,
      "durationTime_ms": 0,
      "faceCenterY": 0.9263601338709933,
      "faceCenterX": 4.582483611026643,
      "rightEye": [
        -11.333586236209392,
        -0.00024900445787778835,
        1.587711294888448,
        0.8765414498646323,
        -0.0032358857958420017,
        0.545704222393813,
        0.5458119077048814,
        0.545704222393813,
        0.5458119077048814,
        0.5459827746513517,
        0.5461034462755464,
        0.5457798504886167,
        0.5458875097413483,
        0.001466602801103667,
        0.0,
        0.00036288952789882223,
        0.0,
        0.0,
        0.0,
        1,
        1.0,
        0.0010475959777832026,
        -0.1000936211488983,
        0.36203885025644744,
        0
      ],
      "triggerTime_ms": 165
    },
    {
      "Name": "ProceduralFaceKeyFrame",
      "faceScaleY": 0.9993613775940985,
      "scanlineOpacity": 1.0,
      "faceScaleX": 1.0003075560835828,
      "leftEye": [
        3.944586732241227,
        0.006090248670290066,
        1.6319547632490918,
        0.7984227335824554,
        0.004388226620419472,
        0.5995949738975418,
        0.5997505099320026,
        0.5995949738975418,
        0.5997505099320026,
        0.5999972508775133,
        0.6001715859710883,
        0.5997040849975053,
        0.599859621031966,
        0.0019902693519093795,
        0.0,
        0.0004920535971509336,
        0.0,
        0.0,
        0.0,
        1,
        1.0,
        0.0014128112792968746,
        -0.0819096014389028,
        0.24310148324254832,
        0
      ],
      "faceAngle": 0.0,
      "durationTime_ms": 0,
      "faceCenterY": -3.26964117328799,
      "faceCenterX": 4.526090370803793,
      "rightEye": [
        -11.582820575933958,
        -0.00031195009984230637,
        1.6745567247293272,
        0.8136747264562558,
        -0.004387641757073901,
        0.5995948245887516,
        0.5997503982698638,
        0.5995948245887516,
        0.5997503982698638,
        0.5999972508775133,
        0.6001715859710883,
        0.5997040849975053,
        0.599859621031966,
        0.0019886139675983072,
        0.0,
        0.0004920535971509336,
        0.0,
        0.0,
        0.0,
        1,
        1.0,
        0.0014128112792968746,
        -0.08252451025162288,
        0.23831112977955038,
        0
      ],
      "triggerTime_ms": 198
    },
    {
      "Name": "ProceduralFaceKeyFrame",
      "faceScaleY": 1.0200078113287627,
      "scanlineOpacity": 1.0,
      "faceScaleX": 1.0002569242153874,
      "leftEye": [
        5.880260520002359,
        0.003258283038604759,
        1.6053919027715526,
        0.8761448682941642,
        0.00432754992802082,
        0.5996616519095535,
        0.5997915825978128,
        0.5996616519095535,
        0.5997915825978128,
        0.5999977034558066,
        0.600169213425163,
        0.5997528004357722,
        0.5998827311240316,
        0.001962749587844592,
        0.0,
        0.0004852498954871835,
        0.0,
        0.0,
        0.0,
        1,
        1.0,
        0.0014152868267271862,
        -0.06342460951165174,
        0.11223644408217681,
        0
      ],
      "faceAngle": 0.0,
      "durationTime_ms": 0,
      "faceCenterY": -3.224234650979198,
      "faceCenterX": 4.462497986929084,
      "rightEye": [
        -11.523362456213817,
        -0.00030760308573007933,
        1.6341815285476207,
        0.910143672411254,
        -0.004326973151671748,
        0.5996615271809402,
        0.5997914893182164,
        0.5996615271809402,
        0.5997914893182164,
        0.5999977034558066,
        0.600169213425163,
        0.5997528004357722,
        0.5998827311240316,
        0.001961117092790121,
        0.0,
        0.0004852498954871835,
        0.0,
        0.0,
        0.0,
        1,
        1.0,
        0.0014152868267271862,
        -0.06402087217896058,
        0.10800214757515869,
        0
      ],
      "triggerTime_ms": 231
    },
    {
      "Name": "ProceduralFaceKeyFrame",
      "faceScaleY": 1.0437623103568172,
      "scanlineOpacity": 1.0,
      "faceScaleX": 1.000198670345528,
      "leftEye": [
        8.107326060759803,
        0.0,
        1.5771153093599788,
        0.9588813342775961,
        0.004257739109884736,
        0.5997383674717605,
        0.5998388382455732,
        0.5997383674717605,
        0.5998388382455732,
        0.5999982241641656,
        0.6001664837217866,
        0.5998088493808749,
        0.5999093201546876,
        0.0019310870635982358,
        0.0,
        0.00047742198066985365,
        0.0,
        0.0,
        0.0,
        1,
        1.0,
        0.0013933813436001322,
        -0.04344588086300649,
        -0.029203547737618085,
        0
      ],
      "faceAngle": 0.0,
      "durationTime_ms": 0,
      "faceCenterY": -3.1719927382153186,
      "faceCenterX": 4.462497986929084,
      "rightEye": [
        -11.454953651804622,
        -0.00030260168238527285,
        1.5912014809993524,
        1.0211348252842087,
        -0.004257171637929484,
        0.599738271023566,
        0.5998387661157834,
        0.599738271023566,
        0.5998387661157834,
        0.5999982241641656,
        0.6001664837217866,
        0.5998088493808749,
        0.5999093201546876,
        0.0019294809034946514,
        0.0,
        0.00047742198066985365,
        0.0,
        0.0,
        0.0,
        1,
        1.0,
        0.0013933813436001322,
        -0.04402199062567891,
        -0.0328368533932237,
        0
      ],
      "triggerTime_ms": 264
    },
    {
      "Name": "ProceduralFaceKeyFrame",
      "faceScaleY": 1.0498822916651671,
      "scanlineOpacity": 1.0,
      "faceScaleX": 0.9557915660420427,
      "leftEye": [
        8.107326060759803,
        0.0,
        1.548838715948405,
        1.041617800261028,
        0.004169211437378718,
        0.5997507627740664,
        0.599846473567831,
        0.5997507627740664,
        0.599846473567831,
        0.5999983082975191,
        0.6001630221624895,
        0.5998179054784709,
        0.5999136162722355,
        0.0018909355562524155,
        0.0,
        0.0004674953375239819,
        0.0,
        0.0,
        0.0,
        1,
        1.0,
        0.0013641861454322909,
        -0.05019328546276769,
        -0.015915935577111365,
        0
      ],
      "faceAngle": 0.0,
      "durationTime_ms": 0,
      "faceCenterY": -3.1062237588514554,
      "faceCenterX": 4.462497986929084,
      "rightEye": [
        -11.369325158158972,
        -0.00029634133859701706,
        1.5482214334510844,
        1.0530380588717374,
        -0.004168655764401777,
        0.5997506708952751,
        0.5998464048553173,
        0.5997506708952751,
        0.5998464048553173,
        0.5999983082975191,
        0.6001630221624895,
        0.5998179054784709,
        0.5999136162722355,
        0.0018893627917166977,
        0.0,
        0.0004674953375239819,
        0.0,
        0.0,
        0.0,
        1,
        1.0,
        0.0013641861454322909,
        -0.050884879429024754,
        -0.017896083033273034,
        0
      ],
      "triggerTime_ms": 297
    },
    {
      "Name": "ProceduralFaceKeyFrame",
      "faceScaleY": 1.0572128187268166,
      "scanlineOpacity": 1.0,
      "faceScaleX": 0.9026006389092969,
      "leftEye": [
        8.107326060759803,
        0.0,
        1.5177059009801064,
        1.1327114850306652,
        0.004063172796684697,
        0.5997656098944107,
        0.5998556191736126,
        0.5997656098944107,
        0.5998556191736126,
        0.599998409072635,
        0.6001588758991558,
        0.5998287528920748,
        0.5999187621712766,
        0.0018428419925086148,
        0.0,
        0.00045560518254716075,
        0.0,
        0.0,
        0.0,
        1,
        1.0,
        0.0013312595647889244,
        -0.05827534152182223,
        -4.527713205392113e-09,
        0
      ],
      "faceAngle": 0.0,
      "durationTime_ms": 0,
      "faceCenterY": -3.027445530822214,
      "faceCenterX": 4.462497986929084,
      "rightEye": [
        -11.266759160275718,
        -0.000288842685044699,
        1.5008999669585465,
        1.0912518221798762,
        -0.004062631256549909,
        0.5997655234888608,
        0.5998555545543194,
        0.5997655234888608,
        0.5998555545543194,
        0.599998409072635,
        0.6001588758991558,
        0.5998287528920748,
        0.5999187621712766,
        0.001841309229257515,
        0.0,
        0.00045560518254716075,
        0.0,
        0.0,
        0.0,
        1,
        1.0,
        0.0013312595647889244,
        -0.059105262720944185,
        4.540733455904444e-09,
        0
      ],
      "triggerTime_ms": 330
    },
    {
      "Name": "ProceduralFaceKeyFrame",
      "faceScaleY": 1.0116125838263643,
      "scanlineOpacity": 1.0,
      "faceScaleX": 0.9460198933560777,
      "leftEye": [
        8.107326060759803,
        0.0,
        1.517704260611263,
        1.1327102481850222,
        0.004036731345130314,
        0.5997691182287488,
        0.5998577802554965,
        0.5997691182287488,
        0.5998577802554965,
        0.599998432885522,
        0.6001578420003775,
        0.5998313161065395,
        0.5999199781332872,
        0.0018308495374235179,
        0.0,
        0.00045264029206259007,
        0.0,
        0.0,
        0.0,
        1,
        1.0,
        0.0013199557493578362,
        -0.057015212803522286,
        -3.824462082607343e-09,
        0
      ],
      "faceAngle": 0.0,
      "durationTime_ms": 0,
      "faceCenterY": -3.010002869623929,
      "faceCenterX": 4.462497986929084,
      "rightEye": [
        -11.246331885286814,
        -0.00028734923632356413,
        1.5009070832322982,
        1.0919279894533094,
        -0.004036193329115212,
        0.599769033116511,
        0.5998577166034202,
        0.599769033116511,
        0.5998577166034202,
        0.599998432885522,
        0.6001578420003775,
        0.5998313161065395,
        0.5999199781332872,
        0.001829326748763127,
        0.0,
        0.00045264029206259007,
        0.0,
        0.0,
        0.0,
        1,
        1.0,
        0.0013199557493578362,
        -0.05782718803253695,
        4.442546108762713e-09,
        0
      ],
      "triggerTime_ms": 363
    },
    {
      "Name": "ProceduralFaceKeyFrame",
      "faceScaleY": 0.9608887270269848,
      "scanlineOpacity": 1.0,
      "faceScaleX": 1.0001719972166696,
      "leftEye": [
        8.107326060759803,
        0.0,
        1.5177024359313134,
        1.1327088723679586,
        0.004003753804427658,
        0.5997734937917997,
        0.5998604755373969,
        0.5997734937917997,
        0.5998604755373969,
        0.5999984625847407,
        0.6001565525311146,
        0.5998345129245798,
        0.5999214946701769,
        0.0018158926552387378,
        0.0,
        0.00044894250730083944,
        0.0,
        0.0,
        0.0,
        1,
        1.0,
        0.0013098235204241334,
        -0.05544359159305812,
        -2.9473736036285848e-09,
        0
      ],
      "faceAngle": 0.0,
      "durationTime_ms": 0,
      "faceCenterY": -2.988248539365395,
      "faceCenterX": 4.462497986929084,
      "rightEye": [
        -11.220855171536606,
        -0.0002854866205055373,
        1.5009149990873702,
        1.09268013057769,
        -0.0040032201836629495,
        0.599773410292569,
        0.5998604130916249,
        0.599773410292569,
        0.5998604130916249,
        0.5999984625847407,
        0.6001565525311146,
        0.5998345129245798,
        0.5999214946701769,
        0.0018143823067979792,
        0.0,
        0.00044894250730083944,
        0.0,
        0.0,
        0.0,
        1,
        1.0,
        0.0013098235204241334,
        -0.05623318476946726,
        4.320087398923533e-09,
        0
      ],
      "triggerTime_ms": 396
    },
    {
      "Name": "ProceduralFaceKeyFrame",
      "faceScaleY": 0.9035041617589998,
      "scanlineOpacity": 1.0,
      "faceScaleX": 1.0001706397227914,
      "leftEye": [
        8.107326060759803,
        0.0,
        1.517700611251364,
        1.132707496550895,
        0.003984283455985859,
        0.5997749988726282,
        0.5998614026448499,
        0.5997749988726282,
        0.5998614026448499,
        0.5999984728005058,
        0.6001557912124923,
        0.5998356125475286,
        0.5999220163197501,
        0.0018053035038634313,
        0.0,
        0.0004467592893822111,
        0.0,
        0.0,
        0.0,
        1,
        1.0,
        0.0013034605948822437,
        -0.05059551404825158,
        -2.6456777900052536e-09,
        0
      ],
      "faceAngle": 0.0,
      "durationTime_ms": 0,
      "faceCenterY": -2.982779217333274,
      "faceCenterX": 4.462497986929084,
      "rightEye": [
        -11.212830613766599,
        -0.0002848999409010844,
        1.5009229149424423,
        1.0934322717020708,
        -0.003983752430231418,
        0.5997749159282305,
        0.5998613406140154,
        0.5997749159282305,
        0.5998613406140154,
        0.5999984728005058,
        0.6001557912124923,
        0.5998356125475286,
        0.5999220163197501,
        0.001803801962831031,
        0.0,
        0.0004467592893822111,
        0.0,
        0.0,
        0.0,
        1,
        1.0,
        0.0013034605948822437,
        -0.05131606391707377,
        3.9423320163933795e-09,
        0
      ],
      "triggerTime_ms": 429
    },
    {
      "Name": "ProceduralFaceKeyFrame",
      "faceScaleY": 0.9996537686632451,
      "scanlineOpacity": 1.0,
      "faceScaleX": 1.0001657558655062,
      "leftEye": [
        8.107326060759803,
        0.0,
        1.5176951372115155,
        1.132703369099704,
        0.003914234961017092,
        0.5997804137036552,
        0.5998647381003993,
        0.5997804137036552,
        0.5998647381003993,
        0.5999985095537759,
        0.60015305221561,
        0.5998395686622756,
        0.5999238930590196,
        0.001767206901788776,
        0.0,
        0.00043890472376700065,
        0.0,
        0.0,
        0.0,
        1,
        1.0,
        0.00128056869034648,
        -0.03315357989279799,
        -1.5602664145557973e-09,
        0
      ],
      "faceAngle": 0.0,
      "durationTime_ms": 0,
      "faceCenterY": -2.963102231171735,
      "faceCenterX": 4.462497986929084,
      "rightEye": [
        -11.18396065305381,
        -0.0002827892430303791,
        1.500946662507658,
        1.095688695075213,
        -0.003913713271334067,
        0.5997803327553805,
        0.5998646775623862,
        0.5997803327553805,
        0.5998646775623862,
        0.5999985095537759,
        0.60015305221561,
        0.5998395686622756,
        0.5999238930590196,
        0.0017657370471798606,
        0.0,
        0.00043890472376700065,
        0.0,
        0.0,
        0.0,
        1,
        1.0,
        0.00128056869034648,
        -0.03362573257455481,
        2.5832807004633196e-09,
        0
      ],
      "triggerTime_ms": 528
    },
    {
      "Name": "ProceduralFaceKeyFrame",
      "faceScaleY": 0.9996645075309434,
      "scanlineOpacity": 1.0,
      "faceScaleX": 1.0001644425568377,
      "leftEye": [
        8.107326060759803,
        0.0,
        1.5176914878516166,
        1.1327006174655767,
        0.0038443478748432344,
        0.5997851358499041,
        0.5998676468724058,
        0.5997851358499041,
        0.5998676468724058,
        0.5999985416054346,
        0.6001503195300436,
        0.5998430186965094,
        0.5999255297190109,
        0.001740414506174126,
        0.0,
        0.0004310682569841915,
        0.0,
        0.0,
        0.0,
        1,
        1.0,
        0.0012584622411186935,
        -0.013040408091167022,
        -6.137047897252804e-10,
        0
      ],
      "faceAngle": 0.0,
      "durationTime_ms": 0,
      "faceCenterY": -2.8827412927106497,
      "faceCenterX": 3.4472828236735733,
      "rightEye": [
        -11.078382053899716,
        -0.0002750703366274365,
        1.5009624942178021,
        1.0971929773239744,
        -0.0038438354997190434,
        0.5997850566424009,
        0.5998675876362469,
        0.5997850566424009,
        0.5998675876362469,
        0.5999985416054346,
        0.6001503195300436,
        0.5998430186965094,
        0.5999255297190109,
        0.0017389669358413018,
        0.0,
        0.0004310682569841915,
        0.0,
        0.0,
        0.0,
        1,
        1.0,
        0.0012584622411186935,
        -0.01322612147932467,
        1.016090211969356e-09,
        0
      ],
      "triggerTime_ms": 594
    },
    {
      "Name": "ProceduralFaceKeyFrame",
      "faceScaleY": 1.0178331287963065,
      "scanlineOpacity": 1.0,
      "faceScaleX": 1.0260901036865404,
      "leftEye": [
        8.107326060759803,
        0.0,
        1.5176893129805653,
        1.132698977602814,
        0.003799036467323919,
        0.5997881974612083,
        0.5998695327795309,
        0.5997881974612083,
        0.5998695327795309,
        0.5999985623861805,
        0.6001485477888522,
        0.5998452555318916,
        0.5999265908502142,
        0.0017230436123142345,
        0.0,
        0.00042598747082834085,
        0.0,
        0.0,
        0.0,
        1,
        1.0,
        0.001244129488322656,
        0.0,
        0.0,
        0
      ],
      "faceAngle": 0.0,
      "durationTime_ms": 0,
      "faceCenterY": -2.830639145796319,
      "faceCenterX": 2.8950496385794446,
      "rightEye": [
        -11.009929995107505,
        -0.00027006577094113027,
        1.5009719292773829,
        1.0980894687651552,
        -0.003798530131309302,
        0.5997881193823373,
        0.5998694743874314,
        0.5997881193823373,
        0.5998694743874314,
        0.5999985623861805,
        0.6001485477888522,
        0.5998452555318916,
        0.5999265908502142,
        0.0017216104900281692,
        0.0,
        0.00042598747082834085,
        0.0,
        0.0,
        0.0,
        1,
        1.0,
        0.001244129488322656,
        0.0,
        0.0,
        0
      ],
      "triggerTime_ms": 627
    },
    {
      "Name": "ProceduralFaceKeyFrame",
      "faceScaleY": 1.044525300778754,
      "scanlineOpacity": 1.0,
      "faceScaleX": 1.0641784206548686,
      "leftEye": [
        8.107326060759803,
        0.0,
        1.5212635898771092,
        1.1374403696498323,
        0.06071345687331296,
        0.5945299114241398,
        0.5966305066205352,
        0.5945299114241398,
        0.5966305066205352,
        0.5999628716682289,
        0.6023739834691447,
        0.5960035136877646,
        0.5981041088841601,
        0.06778595295144552,
        0.0,
        0.02235513079039819,
        0.0,
        0.0,
        0.0,
        1,
        1.0,
        0.018953730806290092,
        0.0,
        0.1558892128374768,
        0
      ],
      "faceAngle": 0.0,
      "durationTime_ms": 0,
      "faceCenterY": -4.024685103728418,
      "faceCenterX": 2.3428159106128037,
      "rightEye": [
        -10.835357274221323,
        -0.00025730266834500526,
        1.5051802393963274,
        1.095429574143679,
        -0.06070536497684098,
        0.5945278949311208,
        0.596628998565163,
        0.5945278949311208,
        0.596628998565163,
        0.5999628716682289,
        0.6023739834691447,
        0.5960035136877646,
        0.5981041088841601,
        0.0699404542085148,
        0.0,
        0.02235513079039819,
        0.0,
        0.0,
        0.0,
        1,
        1.0,
        0.018953730806290092,
        0.0,
        0.1547579452665342,
        0
      ],
      "triggerTime_ms": 660
    },
    {
      "Name": "ProceduralFaceKeyFrame",
      "faceScaleY": 0.9446290952240383,
      "scanlineOpacity": 1.0,
      "faceScaleX": 0.9054024441507331,
      "leftEye": [
        8.107326060759803,
        0.0,
        1.5400285435839636,
        1.1623326778966778,
        0.3595141640047548,
        0.5669239097295298,
        0.5796256192858077,
        0.5669239097295298,
        0.5796256192858077,
        0.5997754953989832,
        0.6140575207906811,
        0.5758343690060986,
        0.5885360785623766,
        0.4146162269818843,
        0.0,
        0.13748313321813935,
        0.0,
        0.0,
        0.0,
        1,
        1.0,
        0.11192913772561894,
        0.0,
        0.9743075802342295,
        0
      ],
      "faceAngle": 0.0,
      "durationTime_ms": 0,
      "faceCenterY": -10.293426382871925,
      "faceCenterX": 0.0,
      "rightEye": [
        -9.918850489568833,
        -0.00019029637970646718,
        1.5272738675207864,
        1.0814651273809288,
        -0.35946624791588166,
        0.5669117165622342,
        0.5796165004982539,
        0.5669117165622342,
        0.5796165004982539,
        0.5997754953989832,
        0.6140575207906811,
        0.5758343690060986,
        0.5885360785623766,
        0.42808938373056893,
        0.0,
        0.13748313321813935,
        0.0,
        0.0,
        0.0,
        1,
        1.0,
        0.11192913772561894,
        0.0,
        0.9672371579158376,
        0
      ],
      "triggerTime_ms": 792
    },
    {
      "Name": "ProceduralFaceKeyFrame",
      "faceScaleY": 0.8263536716924862,
      "scanlineOpacity": 1.0,
      "faceScaleX": 1.0592775974582316,
      "leftEye": [
        8.107326060759803,
        0.0,
        1.5927968356524487,
        1.2021202125081696,
        1.1997615331427978,
        0.4892940054398035,
        0.531806750372595,
        0.4892940054398035,
        0.531806750372595,
        0.5992485809255066,
        0.6469124011920471,
        0.519117398958637,
        0.5616301438914288,
        0.6416119002753394,
        0.0,
        0.16803236613682823,
        0.0,
        0.0,
        0.0,
        1,
        1.0,
        0.3762222327702741,
        0.0,
        1.0000000000000002,
        0
      ],
      "faceAngle": 0.0,
      "durationTime_ms": 0,
      "faceCenterY": -12.967493993472557,
      "faceCenterX": 0.0,
      "rightEye": [
        -8.008896145840403,
        -5.0658622335220116e-05,
        1.5892121738764566,
        1.1802017069390054,
        -1.1996016287885205,
        0.48925319479074325,
        0.5317762297023144,
        0.48925319479074325,
        0.5317762297023144,
        0.5992485809255066,
        0.6469124011920471,
        0.519117398958637,
        0.5616301438914288,
        0.6222117386503452,
        0.0,
        0.16803236613682823,
        0.0,
        0.0,
        0.0,
        1,
        1.0,
        0.3762222327702741,
        0.0,
        0.9781137024292063,
        0
      ],
      "triggerTime_ms": 957
    },
    {
      "Name": "ProceduralFaceKeyFrame",
      "faceScaleY": 0.7840480972106252,
      "scanlineOpacity": 1.0,
      "faceScaleX": 1.1003109677762675,
      "leftEye": [
        8.107326060759803,
        0.0,
        1.6127124832146962,
        1.2171367022528972,
        1.5168851278792124,
        0.45999516415612746,
        0.5137590989749552,
        0.45999516415612746,
        0.5137590989749552,
        0.5990497144748815,
        0.6593123897670834,
        0.4977114534185043,
        0.5514753882373326,
        0.6788074758487559,
        0.0,
        0.17151160760325435,
        0.0,
        0.0,
        0.0,
        1,
        1.0,
        0.4904749670276911,
        0.0,
        1.0000000000000002,
        0
      ],
      "faceAngle": 0.0,
      "durationTime_ms": 0,
      "faceCenterY": -13.459771848828943,
      "faceCenterX": -0.022967160149320875,
      "rightEye": [
        -7.3414957230989515,
        -1.8646296311430888e-06,
        1.6125734871975246,
        1.216000301360467,
        -1.5166829572559792,
        0.4599435527845387,
        0.513720500871488,
        0.4599435527845387,
        0.513720500871488,
        0.5990497144748815,
        0.6593123897670834,
        0.4977114534185043,
        0.5514753882373326,
        0.6704945934613871,
        0.0,
        0.17151160760325435,
        0.0,
        0.0,
        0.0,
        1,
        1.0,
        0.4904749670276911,
        0.0,
        1.0000000000000002,
        0
      ],
      "triggerTime_ms": 1188
    },
    {
      "Name": "ProceduralFaceKeyFrame",
      "faceScaleY": 0.7773789468448858,
      "scanlineOpacity": 1.0,
      "faceScaleX": 1.0712735147142791,
      "leftEye": [
        8.107326060759803,
        0.0,
        1.6135183442977428,
        1.2177443252112479,
        1.5297171265734606,
        0.4588096241984097,
        0.5130288239559637,
        0.4588096241984097,
        0.5130288239559637,
        0.5990416675995398,
        0.6598141393683259,
        0.49684528934311145,
        0.551064489100666,
        0.6937994268443004,
        0.0,
        0.17152779012170283,
        0.0,
        0.0,
        0.0,
        1,
        1.0,
        0.4998785878162282,
        0.0,
        1.0000000000000002,
        0
      ],
      "faceAngle": 0.0,
      "durationTime_ms": 0,
      "faceCenterY": -15.155199143426936,
      "faceCenterX": 0.0,
      "rightEye": [
        -7.315991464547729,
        0.0,
        1.6135183442977428,
        1.2174076617601213,
        -1.529513245699975,
        0.4587575757894648,
        0.5129898990095436,
        0.4587575757894648,
        0.5129898990095436,
        0.5990416675995398,
        0.6598141393683259,
        0.49684528934311145,
        0.551064489100666,
        0.6932223669176385,
        0.0,
        0.17152779012170283,
        0.0,
        0.0,
        0.0,
        1,
        1.0,
        0.4998785878162282,
        0.0,
        1.0000000000000002,
        0
      ],
      "triggerTime_ms": 1815
    },
    {
      "Name": "ProceduralFaceKeyFrame",
      "faceScaleY": 0.7773789468448858,
      "scanlineOpacity": 1.0,
      "faceScaleX": 1.0712735147142791,
      "leftEye": [
        8.107326060759803,
        0.0,
        1.6135183442977428,
        1.2177443252112479,
        1.5297171265734606,
        0.4588096241984097,
        0.5130288239559637,
        0.4588096241984097,
        0.5130288239559637,
        0.5990416675995398,
        0.6598141393683259,
        0.49684528934311145,
        0.551064489100666,
        0.6937994268443004,
        0.0,
        0.17152779012170283,
        0.0,
        0.0,
        0.0,
        1,
        1.0,
        0.5,
        0.0,
        1.0000000000000002,
        0
      ],
      "faceAngle": 0.0,
      "durationTime_ms": 0,
      "faceCenterY": -15.155199143426936,
      "faceCenterX": 0.0,
      "rightEye": [
        -7.315991464547729,
        0.0,
        1.6135183442977428,
        1.2174076617601213,
        -1.529513245699975,
        0.4587575757894648,
        0.5129898990095436,
        0.4587575757894648,
        0.5129898990095436,
        0.5990416675995398,
        0.6598141393683259,
        0.49684528934311145,
        0.551064489100666,
        0.6932223669176385,
        0.0,
        0.17152779012170283,
        0.0,
        0.0,
        0.0,
        1,
        1.0,
        0.5,
        0.0,
        1.0000000000000002,
        0
      ],
      "triggerTime_ms": 1914
    },
    {
      "Name": "ProceduralFaceKeyFrame",
      "faceScaleY": 0.783389715280074,
      "scanlineOpacity": 1.0,
      "faceScaleX": 1.0693491298169937,
      "leftEye": [
        8.107326060759803,
        0.0,
        1.6109245187134988,
        1.2157885688059555,
        1.4884147641559777,
        0.4626217643450526,
        0.5153770457091527,
        0.4626217643450526,
        0.5153770457091527,
        0.5990675425743522,
        0.6581991576053811,
        0.4996304665308474,
        0.5523857478949481,
        0.6750668423195043,
        0.0,
        0.16689653978841687,
        0.0,
        0.0,
        0.0,
        1,
        1.0,
        0.494465,
        0.0,
        0.9730000000000003,
        0
      ],
      "faceAngle": 0.0,
      "durationTime_ms": 0,
      "faceCenterY": -14.746008766554413,
      "faceCenterX": 0.0,
      "rightEye": [
        -7.315991464547729,
        0.0,
        1.6109245187134988,
        1.2154510636457532,
        -1.4882163880660757,
        0.4625711212431492,
        0.5153391717362861,
        0.4625711212431492,
        0.5153391717362861,
        0.5990675425743522,
        0.6581991576053811,
        0.4996304665308474,
        0.5523857478949481,
        0.6745053630108622,
        0.0,
        0.16689653978841687,
        0.0,
        0.0,
        0.0,
        1,
        1.0,
        0.494465,
        0.0,
        0.9730000000000003,
        0
      ],
      "triggerTime_ms": 1947
    },
    {
      "Name": "ProceduralFaceKeyFrame",
      "faceScaleY": 0.1053261265078536,
      "scanlineOpacity": 1.0,
      "faceScaleX": 1.1576758228595412,
      "leftEye": [
        8.107326060759803,
        0.0,
        1.824169375367045,
        1.2102110412797504,
        0.0,
        0.0205778401084394,
        0.0205778401084394,
        0.0205778401084394,
        0.0205778401084394,
        0.0205778401084394,
        0.0205778401084394,
        0.0205778401084394,
        0.0205778401084394,
        0.0,
        0.0,
        0.0,
        0.0,
        0.0,
        0.0,
        1,
        1.0,
        0.4710999999999999,
        0.0,
        0.0,
        0
      ],
      "faceAngle": 0.0,
      "durationTime_ms": 0,
      "faceCenterY": 6.146758230579579,
      "faceCenterX": 0.0,
      "rightEye": [
        -7.315991464547729,
        0.0,
        1.824169375367045,
        1.209871135689962,
        0.0,
        0.0205778401084394,
        0.0205778401084394,
        0.0205778401084394,
        0.0205778401084394,
        0.0205778401084394,
        0.0205778401084394,
        0.0205778401084394,
        0.0205778401084394,
        0.0,
        0.0,
        0.0,
        0.0,
        0.0,
        0.0,
        1,
        1.0,
        0.4710999999999999,
        0.0,
        0.0,
        0
      ],
      "triggerTime_ms": 1980
    },
    {
      "Name": "ProceduralFaceKeyFrame",
      "faceScaleY": 1.1647141657221973,
      "scanlineOpacity": 1.0,
      "faceScaleX": 0.8365307814506014,
      "leftEye": [
        8.107326060759803,
        0.0,
        1.5211354181322778,
        0.9803964884877511,
        0.0,
        0.6,
        0.6,
        0.6,
        0.6,
        0.6,
        0.6,
        0.6,
        0.6,
        0.0,
        0.0,
        0.0,
        0.0,
        0.0,
        0.0,
        1,
        1.0,
        0.07167999999999952,
        0.0,
        -0.0834390014153878,
        0
      ],
      "faceAngle": 0.0,
      "durationTime_ms": 0,
      "faceCenterY": 0.0,
      "faceCenterX": 0.0,
      "rightEye": [
        -7.315991464547729,
        0.0,
        1.5174507300664741,
        1.144941064931666,
        0.0,
        0.6,
        0.6,
        0.6,
        0.6,
        0.6,
        0.6,
        0.6,
        0.6,
        0.0,
        0.0,
        0.0,
        0.0,
        0.0,
        0.0,
        1,
        1.0,
        0.07167999999999952,
        0.0,
        -0.07476658831937502,
        0
      ],
      "triggerTime_ms": 2112
    },
    {
      "Name": "ProceduralFaceKeyFrame",
      "faceScaleY": 0.9732754634350843,
      "scanlineOpacity": 1.0,
      "faceScaleX": 1.027235848930493,
      "leftEye": [
        8.107326060759803,
        0.0,
        1.5174507300664741,
        1.1453089027930028,
        0.0,
        0.6,
        0.6,
        0.6,
        0.6,
        0.6,
        0.6,
        0.6,
        0.6,
        0.0,
        0.0,
        0.0,
        0.0,
        0.0,
        0.0,
        1,
        1.0,
        0.0,
        0.0,
        0.125328012411015,
        0
      ],
      "faceAngle": 0.0,
      "durationTime_ms": 0,
      "faceCenterY": 3.2368673620841406,
      "faceCenterX": 0.0,
      "rightEye": [
        -7.315991464547729,
        0.0,
        1.5174507300664741,
        1.144941064931666,
        0.0,
        0.6,
        0.6,
        0.6,
        0.6,
        0.6,
        0.6,
        0.6,
        0.6,
        0.0,
        0.0,
        0.0,
        0.0,
        0.0,
        0.0,
        1,
        1.0,
        0.0,
        0.0,
        0.125328012411015,
        0
      ],
      "triggerTime_ms": 2244
    },
    {
      "Name": "ProceduralFaceKeyFrame",
      "faceScaleY": 1.0,
      "scanlineOpacity": 1.0,
      "faceScaleX": 1.0,
      "leftEye": [
        8.107326060759803,
        0.0,
        1.5174507300664741,
        1.1453089027930028,
        0.0,
        0.6,
        0.6,
        0.6,
        0.6,
        0.6,
        0.6,
        0.6,
        0.6,
        0.0,
        0.0,
        0.0,
        0.0,
        0.0,
        0.0,
        1,
        1.0,
        0.0,
        0.0,
        0.0,
        0
      ],
      "faceAngle": 0.0,
      "durationTime_ms": 0,
      "faceCenterY": 0.0,
      "faceCenterX": 0.0,
      "rightEye": [
        -7.315991464547729,
        0.0,
        1.5174507300664741,
        1.144941064931666,
        0.0,
        0.6,
        0.6,
        0.6,
        0.6,
        0.6,
        0.6,
        0.6,
        0.6,
        0.0,
        0.0,
        0.0,
        0.0,
        0.0,
        0.0,
        1,
        1.0,
        0.0,
        0.0,
        0.0,
        0
      ],
      "triggerTime_ms": 2409
    },
    {
      "Name": "ProceduralFaceKeyFrame",
      "faceScaleY": 1.0,
      "scanlineOpacity": 1.0,
      "faceScaleX": 1.0,
      "leftEye": [
        8.107326060759803,
        0.0,
        1.5174507300664741,
        1.1453089027930028,
        0.0,
        0.6,
        0.6,
        0.6,
        0.6,
        0.6,
        0.6,
        0.6,
        0.6,
        0.0,
        0.0,
        0.0,
        0.0,
        0.0,
        0.0,
        1,
        1.0,
        0.0,
        0.0,
        0.0,
        0
      ],
      "faceAngle": 0.0,
      "durationTime_ms": 0,
      "faceCenterY": 0.0,
      "faceCenterX": 0.0,
      "rightEye": [
        -7.315991464547729,
        0.0,
        1.5174507300664741,
        1.144941064931666,
        0.0,
        0.6,
        0.6,
        0.6,
        0.6,
        0.6,
        0.6,
        0.6,
        0.6,
        0.0,
        0.0,
        0.0,
        0.0,
        0.0,
        0.0,
        1,
        1.0,
        0.0,
        0.0,
        0.0,
        0
      ],
      "triggerTime_ms": 2508
    },
    {
      "Name": "ProceduralFaceKeyFrame",
      "faceScaleY": 1.0,
      "scanlineOpacity": 1.0,
      "faceScaleX": 1.0,
      "leftEye": [
        8.107326060759803,
        0.0,
        1.5174507300664741,
        1.1453089027930028,
        0.0,
        0.6,
        0.6,
        0.6,
        0.6,
        0.6,
        0.6,
        0.6,
        0.6,
        0.0,
        0.0,
        0.0,
        0.0,
        0.0,
        0.0,
        1,
        1.0,
        0.0,
        0.0,
        0.0,
        0
      ],
      "faceAngle": 0.0,
      "durationTime_ms": 0,
      "faceCenterY": 0.0,
      "faceCenterX": 0.0,
      "rightEye": [
        -7.315991464547729,
        0.0,
        1.5174507300664741,
        1.144941064931666,
        0.0,
        0.6,
        0.6,
        0.6,
        0.6,
        0.6,
        0.6,
        0.6,
        0.6,
        0.0,
        0.0,
        0.0,
        0.0,
        0.0,
        0.0,
        1,
        1.0,
        0.0,
        0.0,
        0.0,
        0
      ],
      "triggerTime_ms": 2574
    },
    {
      "eventGroups": [
        {
          "probabilities": [
            1.0
          ],
          "audioName": [
            "Stop__Robot_Vic_Sfx__Wake_Word_Success_Processing_Stop"
          ],
          "eventIds": [
            2452862642
          ],
          "volumes": [
            1.0
          ]
        }
      ],
      "triggerTime_ms": 0,
      "Name": "RobotAudioKeyFrame"
    },
    {
      "eventGroups": [
        {
          "probabilities": [
            1.0
          ],
          "audioName": [
            "Play__Robot_Vic_Sfx__Emote_Greeting_Goodnight"
          ],
          "eventIds": [
            2199944662
          ],
          "volumes": [
            1.0
          ]
        }
      ],
      "triggerTime_ms": 99,
      "Name": "RobotAudioKeyFrame"
    },
    {
      "eventGroups": [
        {
          "probabilities": [
            1.0
          ],
          "audioName": [
            "Play__Robot_Vic_Sfx__Emote_Greeting_Goodnight_Sleep"
          ],
          "eventIds": [
            2099947214
          ],
          "volumes": [
            1.0
          ]
        }
      ],
      "triggerTime_ms": 627,
      "Name": "RobotAudioKeyFrame"
    },
    {
      "eventGroups": [
        {
          "probabilities": [
            1.0
          ],
          "audioName": [
            "Play__Robot_Vic_Sfx__Scrn_Curious"
          ],
          "eventIds": [
            2558890771
          ],
          "volumes": [
            1.0
          ]
        }
      ],
      "triggerTime_ms": 1947,
      "Name": "RobotAudioKeyFrame"
    },
    {
      "Right": [
        0.0,
        0.0,
        0.0,
        0.0
      ],
      "Name": "BackpackLightsKeyFrame",
      "durationTime_ms": 2574,
      "Back": [
        0.0,
        0.0,
        0.0,
        0.0
      ],
      "Middle": [
        0.0,
        0.0,
        0.0,
        0.0
      ],
      "Front": [
        0.0,
        0.0,
        0.0,
        0.0
      ],
      "triggerTime_ms": 0,
      "Left": [
        0.0,
        0.0,
        0.0,
        0.0
      ]
    },
    {
      "durationTime_ms": 66,
      "speed": -42,
      "triggerTime_ms": 66,
      "Name": "BodyMotionKeyFrame",
      "radius_mm": 23
    },
    {
      "durationTime_ms": 66,
      "speed": 84,
      "triggerTime_ms": 132,
      "Name": "BodyMotionKeyFrame",
      "radius_mm": 334
    },
    {
      "durationTime_ms": 33,
      "speed": -58,
      "triggerTime_ms": 198,
      "Name": "BodyMotionKeyFrame",
      "radius_mm": -9
    },
    {
      "durationTime_ms": 66,
      "speed": -171,
      "triggerTime_ms": 231,
      "Name": "BodyMotionKeyFrame",
      "radius_mm": -104
    },
    {
      "durationTime_ms": 33,
      "speed": -54,
      "triggerTime_ms": 297,
      "Name": "BodyMotionKeyFrame",
      "radius_mm": 16
    },
    {
      "durationTime_ms": 66,
      "speed": 12,
      "triggerTime_ms": 330,
      "Name": "BodyMotionKeyFrame",
      "radius_mm": -27
    },
    {
      "durationTime_ms": 132,
      "speed": 2,
      "triggerTime_ms": 396,
      "Name": "BodyMotionKeyFrame",
      "radius_mm": -1446
    },
    {
      "durationTime_ms": 99,
      "speed": 116,
      "triggerTime_ms": 924,
      "Name": "BodyMotionKeyFrame",
      "radius_mm": -112
    },
    {
      "durationTime_ms": 66,
      "speed": -67,
      "triggerTime_ms": 1089,
      "Name": "BodyMotionKeyFrame",
      "radius_mm": "STRAIGHT"
    },
    {
      "durationTime_ms": 66,
      "speed": 32,
      "triggerTime_ms": 1155,
      "Name": "BodyMotionKeyFrame",
      "radius_mm": "STRAIGHT"
    },
    {
      "durationTime_ms": 66,
      "speed": -58,
      "triggerTime_ms": 1221,
      "Name": "BodyMotionKeyFrame",
      "radius_mm": "STRAIGHT"
    },
    {
      "durationTime_ms": 66,
      "speed": 25,
      "triggerTime_ms": 1287,
      "Name": "BodyMotionKeyFrame",
      "radius_mm": "STRAIGHT"
    },
    {
      "durationTime_ms": 66,
      "speed": -60,
      "triggerTime_ms": 1353,
      "Name": "BodyMotionKeyFrame",
      "radius_mm": "STRAIGHT"
    },
    {
      "durationTime_ms": 66,
      "speed": 32,
      "triggerTime_ms": 1419,
      "Name": "BodyMotionKeyFrame",
      "radius_mm": "STRAIGHT"
    },
    {
      "durationTime_ms": 66,
      "speed": -41,
      "triggerTime_ms": 1485,
      "Name": "BodyMotionKeyFrame",
      "radius_mm": 8418
    },
    {
      "durationTime_ms": 99,
      "speed": 21,
      "triggerTime_ms": 1551,
      "Name": "BodyMotionKeyFrame",
      "radius_mm": -53
    },
    {
      "durationTime_ms": 33,
      "speed": 8,
      "triggerTime_ms": 1914,
      "Name": "BodyMotionKeyFrame",
      "radius_mm": -23
    },
    {
      "durationTime_ms": 66,
      "speed": -45,
      "triggerTime_ms": 1947,
      "Name": "BodyMotionKeyFrame",
      "radius_mm": 17
    },
    {
      "durationTime_ms": 33,
      "speed": -129,
      "triggerTime_ms": 2013,
      "Name": "BodyMotionKeyFrame",
      "radius_mm": -123
    },
    {
      "durationTime_ms": 66,
      "speed": 23,
      "triggerTime_ms": 2046,
      "Name": "BodyMotionKeyFrame",
      "radius_mm": 3
    },
    {
      "durationTime_ms": 33,
      "speed": 172,
      "triggerTime_ms": 2112,
      "Name": "BodyMotionKeyFrame",
      "radius_mm": 126
    },
    {
      "durationTime_ms": 99,
      "speed": 66,
      "triggerTime_ms": 2145,
      "Name": "BodyMotionKeyFrame",
      "radius_mm": -20
    },
    {
      "durationTime_ms": 33,
      "speed": -5,
      "triggerTime_ms": 2244,
      "Name": "BodyMotionKeyFrame",
      "radius_mm": 23
    },
    {
      "durationTime_ms": 66,
      "speed": -2,
      "triggerTime_ms": 2508,
      "Name": "BodyMotionKeyFrame",
      "radius_mm": 23
    }
  ]
}